{
  "updated": "2026-07-01T10:27:46.348Z",
  "count": 30,
  "hi_articles": [
    {
      "title": "जून 2026 में महिंद्रा ट्रैक्टरों की बिक्री 12% बढ़ी, घरेलू बाजार की मजबूत मांग से मिला सहारा",
      "url": "https://www.krishakjagat.org/agriculture-machinery/mahindra-tractor-sales-rose-by-12-in-june-2026-supported-by-strong-domestic-market-demand/",
      "description": "KRISHAK JAGAT | National Agriculture Hindi Newspaper 01 जुलाई 2026, मुंबई: जून 2026 में महिंद्रा ट्रैक्टरों की बिक्री 12% बढ़ी, घरेलू बाजार की मजबूत मांग से मिला सहारा &#8211; महिंद्रा एंड महिंद्रा लिमिटेड के फार्म इक्वि...",
      "source": "Krishak Jagat",
      "image": "https://www.krishakjagat.org/wp-content/uploads/2026/07/Untitled-1-13.jpg",
      "lang": "hi",
      "pubDate": "2026-07-01T10:27:12.172Z"
    },
    {
      "title": "खरीफ 2026: कृषि आदान विक्रेताओं पर कृषि विभाग की सख्ती, 10 नमूने जांच के लिए भेजे",
      "url": "https://www.krishakjagat.org/news/kharif-2026-agriculture-department-cracks-down-on-agri-input-dealers-10-samples-sent-for-testing/",
      "description": "KRISHAK JAGAT | National Agriculture Hindi Newspaper 01 जुलाई 2026, खंडवा: खरीफ 2026: कृषि आदान विक्रेताओं पर कृषि विभाग की सख्ती, 10 नमूने जांच के लिए भेजे &#8211; आगामी खरीफ मौसम 2026 को देखते हुए किसानों को गुणवत्तायु...",
      "source": "Krishak Jagat",
      "image": "https://www.krishakjagat.org/wp-content/uploads/2026/07/wwww.jpg",
      "lang": "hi",
      "pubDate": "2026-07-01T10:27:12.172Z"
    },
    {
      "title": "बाढ़ से तबाह फसलों का लेंगे जायजा, आज अरुणाचल-असम के बाढ़ प्रभावित इलाकों में पहुंचेंगे शिवराज सिंह",
      "url": "https://www.krishakjagat.org/national-news/shivraj-singh-to-assess-flood-ravaged-crops-will-reach-flood-hit-areas-of-arunachal-and-assam-today/",
      "description": "KRISHAK JAGAT | National Agriculture Hindi Newspaper 01 जुलाई 2026, नई दिल्ली: बाढ़ से तबाह फसलों का लेंगे जायजा, आज अरुणाचल-असम के बाढ़ प्रभावित इलाकों में पहुंचेंगे शिवराज सिंह &#8211; केंद्रीय कृषि एवं किसान कल्याण तथ...",
      "source": "Krishak Jagat",
      "image": "https://www.krishakjagat.org/wp-content/uploads/2026/07/Untitled-1-12.jpg",
      "lang": "hi",
      "pubDate": "2026-07-01T10:27:12.172Z"
    },
    {
      "title": "SOMS 2026: स्पेशलिटी फर्टिलाइज़र में आत्मनिर्भरता और नवाचार पर होगा मंथन",
      "url": "https://www.krishakjagat.org/industry-news/soms-2026-deliberations-to-focus-on-self-reliance-and-innovation-in-specialty-fertilizers/",
      "description": "KRISHAK JAGAT | National Agriculture Hindi Newspaper 01 जुलाई 2026, नई दिल्ली: SOMS 2026: स्पेशलिटी फर्टिलाइज़र में आत्मनिर्भरता और नवाचार पर होगा मंथन &#8211; भारत के स्पेशलिटी फर्टिलाइज़र उद्योग को आत्मनिर्भर बनाने और ...",
      "source": "Krishak Jagat",
      "image": "https://www.krishakjagat.org/wp-content/uploads/2026/07/Banner-800x445_20260603_101649_0000-1.jpg",
      "lang": "hi",
      "pubDate": "2026-07-01T10:27:12.172Z"
    },
    {
      "title": "कुक्कुट खाद : कम लागत में उपज बढ़ाने और मिट्टी की सेहत सुधारने का प्रभावी जैविक विकल्प",
      "url": "https://www.krishakjagat.org/news/poultry-manure-an-effective-organic-option-to-boost-yields-and-improve-soil-health-at-a-low-cost/",
      "description": "KRISHAK JAGAT | National Agriculture Hindi Newspaper 01 जुलाई 2026, भोपाल: कुक्कुट खाद : कम लागत में उपज बढ़ाने और मिट्टी की सेहत सुधारने का प्रभावी जैविक विकल्प &#8211; आधुनिक कृषि ने देश में खाद्यान्न उत्पादन बढ़ाने मे...",
      "source": "Krishak Jagat",
      "image": "https://www.krishakjagat.org/wp-content/uploads/2026/07/Untitled-1-11.jpg",
      "lang": "hi",
      "pubDate": "2026-07-01T10:27:12.172Z"
    },
    {
      "title": "सतत कृषि विकास में महिलाओं की भूमिका पर राष्ट्रीय मंथन, पूसा सम्मेलन में जारी हुआ भविष्य का रोडमैप",
      "url": "https://www.krishakjagat.org/national-news/national-deliberation-on-the-role-of-women-in-sustainable-agricultural-development-future-roadmap-unveiled-at-the-pusa-conference/",
      "description": "KRISHAK JAGAT | National Agriculture Hindi Newspaper 01 जुलाई 2026, नई दिल्ली: सतत कृषि विकास में महिलाओं की भूमिका पर राष्ट्रीय मंथन, पूसा सम्मेलन में जारी हुआ भविष्य का रोडमैप &#8211; डॉ. राजेंद्र प्रसाद केंद्रीय कृषि ...",
      "source": "Krishak Jagat",
      "image": "https://www.krishakjagat.org/wp-content/uploads/2026/07/wrrr-1.jpg",
      "lang": "hi",
      "pubDate": "2026-07-01T10:27:12.172Z"
    },
    {
      "title": "रबी सीजन में किसानों को दिन में मिलेगी बिजली, मुख्यमंत्री डॉ. मोहन यादव का बड़ा ऐलान",
      "url": "https://www.krishakjagat.org/news/farmers-to-receive-electricity-during-the-day-in-the-rabi-season-major-announcement-by-chief-minister-dr-mohan-yadav/",
      "description": "KRISHAK JAGAT | National Agriculture Hindi Newspaper 01 जुलाई 2026, भोपाल: रबी सीजन में किसानों को दिन में मिलेगी बिजली, मुख्यमंत्री डॉ. मोहन यादव का बड़ा ऐलान &#8211; मध्यप्रदेश के किसानों के लिए राहत भरी खबर है। मुख्यम...",
      "source": "Krishak Jagat",
      "image": "https://www.krishakjagat.org/wp-content/uploads/2026/07/Untitled-1-10.jpg",
      "lang": "hi",
      "pubDate": "2026-07-01T10:27:12.172Z"
    },
    {
      "title": "आरएचबी बाजरा : कम अवधि में अधिक उत्पादन देने वाली पोषक तत्वों से भरपूर उन्नत किस्म",
      "url": "https://www.krishakjagat.org/crop-cultivation/rhb-bajra-a-nutrient-rich-high-yielding-short-duration-improved-variety/",
      "description": "KRISHAK JAGAT | National Agriculture Hindi Newspaper 01 जुलाई 2026, नई दिल्ली: आरएचबी बाजरा : कम अवधि में अधिक उत्पादन देने वाली पोषक तत्वों से भरपूर उन्नत किस्म &#8211; यदि किसान कम समय में अधिक उपज, बेहतर पोषण गुणवत्ता...",
      "source": "Krishak Jagat",
      "image": "https://www.krishakjagat.org/wp-content/uploads/2026/07/Untitled-1-9.jpg",
      "lang": "hi",
      "pubDate": "2026-07-01T10:27:12.172Z"
    },
    {
      "title": "किसान सारथी : डिजिटल खेती का भरोसेमंद साथी, मिल रही खेती की हर जरूरी जानकारी",
      "url": "https://www.krishakjagat.org/news/kisan-sarathi-a-trusted-companion-for-digital-farming-providing-all-essential-agricultural-information/",
      "description": "KRISHAK JAGAT | National Agriculture Hindi Newspaper 01 जुलाई 2026, भोपाल: किसान सारथी : डिजिटल खेती का भरोसेमंद साथी, मिल रही खेती की हर जरूरी जानकारी &#8211; भारत में कृषि क्षेत्र तेजी से डिजिटल तकनीक को अपनाते हुए आधु...",
      "source": "Krishak Jagat",
      "image": "https://www.krishakjagat.org/wp-content/uploads/2026/07/Untitled-1-8.jpg",
      "lang": "hi",
      "pubDate": "2026-07-01T10:27:12.172Z"
    },
    {
      "title": "खरीफ 2026-27 : किसानों के लिए शुरू हुई ऑनलाइन खाद टोकन बुकिंग, अब लंबी कतारों से मिलेगी राहत",
      "url": "https://www.krishakjagat.org/news/kharif-2026-27-online-fertilizer-token-booking-launched-for-farmers-relief-from-long-queues-now/",
      "description": "KRISHAK JAGAT | National Agriculture Hindi Newspaper 01 जुलाई 2026, भोपाल: खरीफ 2026-27 : किसानों के लिए शुरू हुई ऑनलाइन खाद टोकन बुकिंग, अब लंबी कतारों से मिलेगी राहत &#8211; मध्यप्रदेश के किसानों के लिए राहत भरी खबर है...",
      "source": "Krishak Jagat",
      "image": "https://www.krishakjagat.org/wp-content/uploads/2026/07/Untitled-1-7.jpg",
      "lang": "hi",
      "pubDate": "2026-07-01T10:27:12.172Z"
    },
    {
      "title": "साप्ताहिक मंडी भाव और क्रॉप प्राइस विश्लेषण: अनाज, दालों और तेलहन फसलों के भाव में उतार-चढ़ाव - Tractor Junction",
      "url": "https://news.google.com/rss/articles/CBMimwFBVV95cUxOSnliRVM3ZmlnTXpmS3FldERza0JSM3FFOW1pSHlEdDdYVjVudEN4Sm1LY3NWNEhzbVJ2blJ0VmU5dnBITURQYkw5TnJBa2hQb0o5RmRPRmJCTEx3QVVLcVB2bGlBV0d2N3hUc3kyVDF3SG1GelZzWC05cnk4Rkt4eWdQbHVsckdIWFNnVlFZZWlMajB5dTFucmhKc9IBowFBVV95cUxQRnBFUTF6Mm8xTjF1RGhYcXN5QVJVTlMxdFdtMlFEZEQzQm11RFlGcEtLSHdIVk5CUlpPMF9CZkRuSTN5NGh4OG80dTZVRmlvNzBNbUtlZzJiWVVuWHYwREtlTjd5RUhFMGM1Nkx0Y3QxeHB4LVZYZGtwVFdWOE9KUTVTWjJfMUpJZkhKYmlCVWYwOXoyR25MYjVFMVI3elFvZTZF?oc=5",
      "description": "<a href=\"https://news.google.com/rss/articles/CBMimwFBVV95cUxOSnliRVM3ZmlnTXpmS3FldERza0JSM3FFOW1pSHlEdDdYVjVudEN4Sm1LY3NWNEhzbVJ2blJ0VmU5dnBITURQYkw5TnJBa2hQb0o5RmRPRmJCTEx3QVVLcVB2bGlBV0d2N3hUc3kyVDF3SG1GelZzWC05cnk4Rk...",
      "source": "Tractor Junction",
      "image": "",
      "lang": "hi",
      "pubDate": "2026-07-01T10:27:16.118Z"
    },
    {
      "title": "155261 पर किसान कल से करें कॉल, AI बताएगा मौसम, सरकारी योजनाओं, मंडी भाव, फसल का हाल - ndtv.in",
      "url": "https://news.google.com/rss/articles/CBMixAFBVV95cUxPWnUxRkp2SkpibzdraWdQQWltZEloSjdDbEF6VHZmU1BEcU1BbERJSUI1ZVo1MUlkejVYX3lNY1o5QVpsNTRUSTN1YllaaHdnUS1TQk16aEpMRG0zME1NSkUzY0c4NjNJWlJsOEtCdGpib3phOFlsMENrQzJSMVRuNV92WTllYS1TOEwtRkgweDZfMzFDZFVqQ0wxTzU4N3BYN0MyRFR4ZW1waWJDdVJkYUY1T3ItQllRa1l3M0JWNXhfT3Jm?oc=5",
      "description": "<a href=\"https://news.google.com/rss/articles/CBMixAFBVV95cUxPWnUxRkp2SkpibzdraWdQQWltZEloSjdDbEF6VHZmU1BEcU1BbERJSUI1ZVo1MUlkejVYX3lNY1o5QVpsNTRUSTN1YllaaHdnUS1TQk16aEpMRG0zME1NSkUzY0c4NjNJWlJsOEtCdGpib3phOFlsMENrQzJSMV...",
      "source": "ndtv.in",
      "image": "",
      "lang": "hi",
      "pubDate": "2026-07-01T10:27:16.118Z"
    },
    {
      "title": "5 काम जो किसानों के लिए भारत-विस्तार प्लेटफॉर्म से आसान हो जाएंगे? ये काम कैसे करेगा - News18 Hindi",
      "url": "https://news.google.com/rss/articles/CBMi1AFBVV95cUxPUmhaNnRSQkIzQWtLWDVWaWZzd1FmUURXZFdWNjFyMmVicGpaajYzTXpWaUdXd2dvMHNJNVU5bmhvOG1md3N5SEw5WEVzdEhCR0JnM0stSTFCLTZSVVVCYi05SVo2Ykd0NElQU1AyR2U3NU1uREtpMERlbmgxbVRLOWwyUUR5S2Q5VGFEeldMSjF4WDVoQ2NrTFYtUmxoMmkyWGU1cmpGcGYwUmw0Szl6bXlENkxEUHNSQW1nenptLWFfdWJOckgyWVlqaFAzR3Zmczlqd9IB2gFBVV95cUxObk1Kem5nY1pVbDI3blZWRjR1a2xFQU83NTJoYXJNQ0J5TXZBNEI0QnlfR1V0dVduODN6d2N4XzR5eWdfeW1DR3o3Z21IZUUwd3JPb0NJdm9kcFg1eVFlUFhacmFkZFg1UWh4Z2Q1UWpCUU5Ba21VT2g2TGgzci1uc2xsSFhqMjVwbThKbjRnSGpNRU9rRU05VVE5NU1WcW1tUldsV2JQWWZJWUlSOER6S2lRMU9xOG5QZjJLQ210Uy1wZWwzQXNTQ3dyOGJZWWdKbWx1bUtGLTNIUQ?oc=5",
      "description": "<a href=\"https://news.google.com/rss/articles/CBMi1AFBVV95cUxPUmhaNnRSQkIzQWtLWDVWaWZzd1FmUURXZFdWNjFyMmVicGpaajYzTXpWaUdXd2dvMHNJNVU5bmhvOG1md3N5SEw5WEVzdEhCR0JnM0stSTFCLTZSVVVCYi05SVo2Ykd0NElQU1AyR2U3NU1uREtpMERlbmgxbV...",
      "source": "News18 Hindi",
      "image": "",
      "lang": "hi",
      "pubDate": "2026-07-01T10:27:16.118Z"
    },
    {
      "title": "300 रुपये कुंतल पर आलू 20 रुपये किलो पर बिक्री, उत्तर भारत की मंडियों में औंधे गिरे दाम, लागत निकालने को जूझ रहे किसान - Jansatta",
      "url": "https://news.google.com/rss/articles/CBMizgFBVV95cUxQQnFXTzNfZk1DMTd5dUE3WHByNU9YbnBoSUhzLUplYzVQcld1LU9YUXNIZHNtUHJoSlRTY3JtOXRxVzQwU3BYR2xJcVFlOUt2X282aXBFQXFGRU9mTjhIOHNwckJsUDRmSWxJdXVsMmFyQjVLQWs1eFdrQW9aQk1vTlVTWFpGd3didFRqVU83Y1g1TmdGVGZvMFByenZVUUZyZmNuX2FVck5nNUExQl9ORGszOXlEcXhHdmwzckhnN3ZPNFFCYVBmUjlhLXoxZ9IB1AFBVV95cUxQZGUta2Jnb3VEN3A3WlU0R0l2eWhaNUtrNXNNbVo2Wm5SbWRtTWN6S01IOG5OY250VUZTT0ZqakMya2ZudVgxZ19NLWt0YmpsYTFKdThhMFVpUUs1N0VZNmlkRjllcTBIeFhjT2dnYUY5TjNqT0xvM2dyTTI5NUR3R1RxXzVocWdtUmRTRW0welZFUFBhRWdmajNsa1UwMzJEN2dCQjlIMFZEWktqZEtMWHh6ZGZJRVlleXFkazhMYWVuU3lBREtJX1lMd3hxMmh1WC1Odg?oc=5",
      "description": "<a href=\"https://news.google.com/rss/articles/CBMizgFBVV95cUxQQnFXTzNfZk1DMTd5dUE3WHByNU9YbnBoSUhzLUplYzVQcld1LU9YUXNIZHNtUHJoSlRTY3JtOXRxVzQwU3BYR2xJcVFlOUt2X282aXBFQXFGRU9mTjhIOHNwckJsUDRmSWxJdXVsMmFyQjVLQWs1eFdrQW9aQk...",
      "source": "Jansatta",
      "image": "",
      "lang": "hi",
      "pubDate": "2026-07-01T10:27:16.118Z"
    },
    {
      "title": "Explained: अब AI से खेती का होगा समाधान, किसानों के लिए 'भारत-विस्तार' लॉन्च, जानिए क्या - क्या होंगे काम - Mint",
      "url": "https://news.google.com/rss/articles/CBMi3AFBVV95cUxNWUFMYWlLUzdjeDY0V0hlWkhHLTFjVmdIVDdMNV9WRzhsNEdaS3FZdDZjYjJjcHRVQTZzWHh2XzBsaDJ5bDJyZFVjdlZaZEdnT2xaWEgxNUxKV3ZsdEd4SFIxLTJaQUlKdVgtWHFmZFlIcDBhMEpRSlBpVUx2WHNqOTdpN3g1emE2Sk1qUWViYVFiMXdBaHJwQV9rZ090d2pEYm96NVhudVNldVhJWDY4Nkg0Rkp3Ql93R1pOU3VxSFNKOEpnNUp5clk5SGpYVV9VQU9Uc1c3TnlxZkVR0gHiAUFVX3lxTE00UXdZem5zNm03bU9DZjNNQkg3RGJMaG1yLXBjbTNEWmo1Y1lYMnRoN1N1NUttcGUxQ0RPMmxrVFFNYzZodlc3enVpU2tFamVyOTJGOFkxbVEtYnpiYUdEbHhUbU5PU0ZVSEdNTU1OVV9STGJCSHMwRFREdk1PYS1GX1M5bnc1U0lra0NQaEZwVFN3dFJuY2VaTlRnV1pLa0xJdHNzbkI1aFBiU2hfV0Fub2ZNbkk0S0o3Vm1QUFlEZXZjcVA5TmRtd2xTcDl1UGlIWUEwb1FhUkUtME80aHNscVE?oc=5",
      "description": "<a href=\"https://news.google.com/rss/articles/CBMi3AFBVV95cUxNWUFMYWlLUzdjeDY0V0hlWkhHLTFjVmdIVDdMNV9WRzhsNEdaS3FZdDZjYjJjcHRVQTZzWHh2XzBsaDJ5bDJyZFVjdlZaZEdnT2xaWEgxNUxKV3ZsdEd4SFIxLTJaQUlKdVgtWHFmZFlIcDBhMEpRSlBpVUx2WH...",
      "source": "Mint",
      "image": "",
      "lang": "hi",
      "pubDate": "2026-07-01T10:27:16.118Z"
    }
  ],
  "en_articles": [
    {
      "title": "Location-Specific Production Technologies Transform Rice-Based Farming and Water Productivity in a Tribal Cluster of Odisha | ICAR - Indian Council Of Agricultural Research",
      "url": "https://news.google.com/rss/articles/CBMitwFBVV95cUxNTmY3VjNVZTVMbTNpcmVTUURveE93U1AxdW1ocktrLWtldVlWTVZPUXJUdGpFYmJTOVZRZk9TRVotWHN4UkJTd1JFcV9rTURCQklWZ25YMTZ6b29mQzI5b19UaWpoVFFaWkJqU3FPVWh5TjRIckNBdDFVWE9fV3hPVDgzWXh6NzVJM3diQ09oRlRMQm1fQ0hHbWpwVEJyVXM1Wm5wU2h3czFQbjJ5SmpNTE9KanJnQjg?oc=5",
      "description": "<a href=\"https://news.google.com/rss/articles/CBMitwFBVV95cUxNTmY3VjNVZTVMbTNpcmVTUURveE93U1AxdW1ocktrLWtldVlWTVZPUXJUdGpFYmJTOVZRZk9TRVotWHN4UkJTd1JFcV9rTURCQklWZ25YMTZ6b29mQzI5b19UaWpoVFFaWkJqU3FPVWh5TjRIckNBdDFVWE9fV3...",
      "source": "Indian Council Of Agricultural Research",
      "image": "",
      "lang": "en",
      "pubDate": "2026-07-01T10:27:20.538Z"
    },
    {
      "title": "Farming worries after India records driest June in over a decade - BBC",
      "url": "https://news.google.com/rss/articles/CBMiXEFVX3lxTE9lSERKLVdBUlpJOTY0WUF4QXBaTXVvclU0Wndkck1lYV9Md2VNRUF4QnV5MmxrbWZneUh0VVJZXzJYQmtwbDAyVVExMl9JWjNpQ3R4YXdWX0tndzl3?oc=5",
      "description": "<a href=\"https://news.google.com/rss/articles/CBMiXEFVX3lxTE9lSERKLVdBUlpJOTY0WUF4QXBaTXVvclU0Wndkck1lYV9Md2VNRUF4QnV5MmxrbWZneUh0VVJZXzJYQmtwbDAyVVExMl9JWjNpQ3R4YXdWX0tndzl3?oc=5\" target=\"_blank\">Farming worries after I...",
      "source": "BBC",
      "image": "",
      "lang": "en",
      "pubDate": "2026-07-01T10:27:20.538Z"
    },
    {
      "title": "How Satellite Data Is Helping Farmers Access Faster Agricultural Loans in India - The Better India",
      "url": "https://news.google.com/rss/articles/CBMilAFBVV95cUxOTUVrQVJYNUIwYUVPYUUydXNHNVE2RWhzVXdLNm1LOC1BODdlX0FJSm5HNlF1Sk5SbVNjTzhwQ0tXUEJBbmFtU2NIUHVRU0VaMlAxNGJuX1lvRDkyZTExUkF1cHIxd1JoV3ZYV2dNand1Wk9TZHMyQW1YOUttcnVOaXJ2WHR6RGVRT3ZBSVdXa2Z0N3pQ0gGaAUFVX3lxTE8zck9TTEpnM1ZvVzc0YTlzdXpINi1lZ193UlVkY0FxM3ZCMHhmOTU5VmE4b281NnVNNXgwMGt1d240cTRqOW1iOTBSblhfYXRJSzExS2R0X1c2UmRETDdzQWpQSnkzRHNyaTRnTk4tekpFZnJiT3FhdUZHSnVKbzFqWjRObG5qd0hHQl90dld3WldxUDF6ZlBhMnc?oc=5",
      "description": "<a href=\"https://news.google.com/rss/articles/CBMilAFBVV95cUxOTUVrQVJYNUIwYUVPYUUydXNHNVE2RWhzVXdLNm1LOC1BODdlX0FJSm5HNlF1Sk5SbVNjTzhwQ0tXUEJBbmFtU2NIUHVRU0VaMlAxNGJuX1lvRDkyZTExUkF1cHIxd1JoV3ZYV2dNand1Wk9TZHMyQW1YOUttcn...",
      "source": "The Better India",
      "image": "",
      "lang": "en",
      "pubDate": "2026-07-01T10:27:20.538Z"
    },
    {
      "title": "India’s Agricultural Transformation (2014-2026), Key Reforms, Growth - Vajiram & Ravi",
      "url": "https://news.google.com/rss/articles/CBMihAFBVV95cUxOVzNKSE55MXV5ald3SFZZVEJ5a1ZLV0lXeFBCTmVhcGNhYWF5WnlncXVaazEtYXBaNVRkTkxld3ZydUwxWGdIY2ttUGhoWkcxeE5zX0oyUjFiaXctZ2xSV19INDJmSmVUUHZfaUVIbS15UlFmWFZ4NHhuZUJiaVRpM0tmTEI?oc=5",
      "description": "<a href=\"https://news.google.com/rss/articles/CBMihAFBVV95cUxOVzNKSE55MXV5ald3SFZZVEJ5a1ZLV0lXeFBCTmVhcGNhYWF5WnlncXVaazEtYXBaNVRkTkxld3ZydUwxWGdIY2ttUGhoWkcxeE5zX0oyUjFiaXctZ2xSV19INDJmSmVUUHZfaUVIbS15UlFmWFZ4NHhuZUJiaV...",
      "source": "Vajiram &amp; Ravi",
      "image": "",
      "lang": "en",
      "pubDate": "2026-07-01T10:27:20.538Z"
    },
    {
      "title": "How natural farming is transforming food production in southern India - UNEP - UN Environment Programme",
      "url": "https://news.google.com/rss/articles/CBMiqwFBVV95cUxORlJfNzlzNzJPU1gxVExwSnNXZkVwaktXcktDNndaUVFHMW5yRk52VEFWbUZQTTBPSXpVOHh4by1rc1d2TklxRHhTYWlNdFVWemhUbFFuTVM4eXdicjhXaVBGNDlRLTQ3QmhWY3hscjVXd3A4TnFvMHZwSHZVMlZGelV1ZDg3Y3RuN1A4dGw4TG9WcVVnNTI0R01hNTlEcExxMEFYcnBqV2x0eHc?oc=5",
      "description": "<a href=\"https://news.google.com/rss/articles/CBMiqwFBVV95cUxORlJfNzlzNzJPU1gxVExwSnNXZkVwaktXcktDNndaUVFHMW5yRk52VEFWbUZQTTBPSXpVOHh4by1rc1d2TklxRHhTYWlNdFVWemhUbFFuTVM4eXdicjhXaVBGNDlRLTQ3QmhWY3hscjVXd3A4TnFvMHZwSHZVMl...",
      "source": "UNEP - UN Environment Programme",
      "image": "",
      "lang": "en",
      "pubDate": "2026-07-01T10:27:20.538Z"
    },
    {
      "title": "Empowering Agricultural Communities through AI-Powered Solutions - orfonline.org",
      "url": "https://news.google.com/rss/articles/CBMipgFBVV95cUxONVdrNERDYkM3Y1NPblBmbWlQYTNnVXhqdVduOFJLMVdSakpfbVJtd0Q2RkJZdWlaN2lCVlRNb0ZMRzJzVjVvdFM3NGlZTGRkZUFqY0tzTi1tNmM3WkZBcEZiY1ZrcE15M0VYN3pLSG9WQ3NzVWNTajJrTkowckxPUzd0ZjZ1Mi11SXNGNlppeUFSTUNwNnRkYUI3c1dPd0J5WlY0UjJR?oc=5",
      "description": "<a href=\"https://news.google.com/rss/articles/CBMipgFBVV95cUxONVdrNERDYkM3Y1NPblBmbWlQYTNnVXhqdVduOFJLMVdSakpfbVJtd0Q2RkJZdWlaN2lCVlRNb0ZMRzJzVjVvdFM3NGlZTGRkZUFqY0tzTi1tNmM3WkZBcEZiY1ZrcE15M0VYN3pLSG9WQ3NzVWNTajJrTkowck...",
      "source": "orfonline.org",
      "image": "",
      "lang": "en",
      "pubDate": "2026-07-01T10:27:20.538Z"
    },
    {
      "title": "Universal crop insurance coverage essential for India's agricultural resilience: AIC CMD Lavanya Mundayur - ETGovernment.com",
      "url": "https://news.google.com/rss/articles/CBMi4wFBVV95cUxNeXdLc3VLbllFVzc3eGx3ckpSUU9fZ0NyY1ZVMVgya2pFdV9HTmxGNHU3MWdoRHpUTGYxNC1HNjE3V1kwRG1ncExmWE9aYUFZTFJLUEZJaXhBN244UEFYbHVHUkpXb2hyQTZKc3Z4aXBUMmlNdU5QdC1FS3J5enNHQzRqWW1aUUd6RnczX3Uwa2czSGhINVBpOHpPSGJ5NE5YWmxFZFFJR3o2ZHN6N2pqNFpMaU5zRGNxWWgwUHdsenEyYndiY3dyWFc4TUFsazg4bVJwamxZZTZPT0d3Skt2ZktxONIB6AFBVV95cUxPcUFoM29Yb1I3VnBCay0xbVJBQ1VkUFl1QzlJLUtzdkNBNkgxR1FuVGNtU2ZGZGJzbkRkc0NjT2h0dDJNSWFLUjQ2STltUVlfQko2TmZrTlJEWUlWay1HVmhzUWI4dEdBaEV1bFhUYTBzaGdmMVlBWDllZDhma1FvTUc3aG9zOFFBRExmSTI2clU4RmRrMnNJQTZhaE5uWURFU200eEpZd20tdFhHNWlqVFp6TURfdUtNYzh2QWQzajNvV3BLbVZBOFF4a2xUNUNFamVZVzR0VmJlQkdLZWQ0N0lyLXZJcnc5?oc=5",
      "description": "<a href=\"https://news.google.com/rss/articles/CBMi4wFBVV95cUxNeXdLc3VLbllFVzc3eGx3ckpSUU9fZ0NyY1ZVMVgya2pFdV9HTmxGNHU3MWdoRHpUTGYxNC1HNjE3V1kwRG1ncExmWE9aYUFZTFJLUEZJaXhBN244UEFYbHVHUkpXb2hyQTZKc3Z4aXBUMmlNdU5QdC1FS3J5en...",
      "source": "ETGovernment.com",
      "image": "",
      "lang": "en",
      "pubDate": "2026-07-01T10:27:20.538Z"
    },
    {
      "title": "India’s Agricultural Revolution: Rising output, record procurement and expanding farmer support since 2014 - organiser.org",
      "url": "https://news.google.com/rss/articles/CBMi5gFBVV95cUxQTXFXckZhU1Zza0l4WFlhdFVWS0JDQUtkd0Z2dmVSRmlYNWM2UUhTWGw4RW10Vy0zYU8zcWdVa1lQUnNDLS1FTWZmT1ltN2JXZFVhUGtST25qaHBMRzM0SENGOUZ3Qmdtd01rYlZhUjNfR1FVTDd5VzRQZndnaFgtSHBTT29lVFRYdS00OGFFZU1jdFpoMzUyVkVFUnBwdDgyUjdsUVFpOENjV0JEMW1YRERvRHoxaENRVTFYMDE2TFJUXy1FdjdDSUJBQ2FIX2N3QlJfS296UW5XZGJ2S1k2ZzB1a1oyd9IB6wFBVV95cUxNakktN0szUFNSZnJjd0VUdHBWTFpURGhmWFc4RDA2RnVfaWI3T1MzNGJFT0Q1bG1uT0loTWdkaFQzNXc3dmlTaXdVNzNWWWJxZTg2UGZMaHg4aUx1eE92SGowdW1SNlYtNXdPUWRGdWNXZzRPd3FxOEJnZXRzTGxXZ3FJdGttTWFDeU84YkxIQVFXZ2pTMlJBcjRsSUtkR1VUUmxTelh3UTN0NVVtamFzOHBMNUZGMUZmREJqQkhnOW9vdEV0ZkMwR2tzTURMOWdzWHJGdk8tbHFSUEZINEl1Rm0weDBKdGQ3VWZJ?oc=5",
      "description": "<a href=\"https://news.google.com/rss/articles/CBMi5gFBVV95cUxQTXFXckZhU1Zza0l4WFlhdFVWS0JDQUtkd0Z2dmVSRmlYNWM2UUhTWGw4RW10Vy0zYU8zcWdVa1lQUnNDLS1FTWZmT1ltN2JXZFVhUGtST25qaHBMRzM0SENGOUZ3Qmdtd01rYlZhUjNfR1FVTDd5VzRQZndnaF...",
      "source": "organiser.org",
      "image": "",
      "lang": "en",
      "pubDate": "2026-07-01T10:27:20.538Z"
    },
    {
      "title": "From CowGPT To Carbon Credits: 4 Indian Innovations Helping Farmers Cut Risk & Earn More - The Better India",
      "url": "https://news.google.com/rss/articles/CBMiwwFBVV95cUxQTlNoYTV3OWpFajhwdjNSUVdWRi10VmZfTWRZSm1jLUd2NFp6dUo5d2JsUll3ZXVSN19vcHZXWXJtNUUwR2pIam45ay16V0FhRFZWYXNjZG9qcG9YUkZ4OHJlV1JJNjB1S2xpLTJuNnEzc3ZtR0VELVVvbWlWcnRxYjBvUFZTTVFjVTRCQTBtUk1abjNNbzBnSFYzZkR6MWppRWJNWWZ5XzJWdFlzcDlXWnFySW40cm5rV2VlNDltck1mQjjSAcgBQVVfeXFMUEFhRjVXSkhONEQtSDdlUy1rRjNnaGdsMXNMM2YxaDBaTlFwQTlxSnV3bUp0YzVqVXozUkRBQ1BkMzhfRWRZVmpwUTJydUJxaW9UbnFJV0JHX3IxRWhFZUVnb3RSQUdHa1AtczJBOVV0Nl9fMG95MF9tWVduSTY4Y3ExWTFaOWZoZkpmaVdvQlRYNU0yX0p0cFByZDFINXZfeDFEREVla0FNMzZZYXhtZ21zd0ZPdjY2aHVJcUt1NXpFazhyMGpadDA?oc=5",
      "description": "<a href=\"https://news.google.com/rss/articles/CBMiwwFBVV95cUxQTlNoYTV3OWpFajhwdjNSUVdWRi10VmZfTWRZSm1jLUd2NFp6dUo5d2JsUll3ZXVSN19vcHZXWXJtNUUwR2pIam45ay16V0FhRFZWYXNjZG9qcG9YUkZ4OHJlV1JJNjB1S2xpLTJuNnEzc3ZtR0VELVVvbWlWcn...",
      "source": "The Better India",
      "image": "",
      "lang": "en",
      "pubDate": "2026-07-01T10:27:20.538Z"
    },
    {
      "title": "Closing the Gender Gap in Crop Insurance - orfonline.org",
      "url": "https://news.google.com/rss/articles/CBMihgFBVV95cUxOdmE2Y2NiZ1E2OEM3MGlDTkFqbWRYTjU4S2hBNUtOakdfenJyVFFfUVowLXRsT3g2NzRYRHNoYk5Xay1PZnI0WXRWY2RKWUpoZ0wtQTFfbUZ2aHVYbm9odDY1R1pOWHFyclY3REVoeWVpVHJqaEJ2Vzl6Y3lPdVVGTWdac2xTQQ?oc=5",
      "description": "<a href=\"https://news.google.com/rss/articles/CBMihgFBVV95cUxOdmE2Y2NiZ1E2OEM3MGlDTkFqbWRYTjU4S2hBNUtOakdfenJyVFFfUVowLXRsT3g2NzRYRHNoYk5Xay1PZnI0WXRWY2RKWUpoZ0wtQTFfbUZ2aHVYbm9odDY1R1pOWHFyclY3REVoeWVpVHJqaEJ2Vzl6Y3lPdV...",
      "source": "orfonline.org",
      "image": "",
      "lang": "en",
      "pubDate": "2026-07-01T10:27:20.538Z"
    },
    {
      "title": "Artificial Intelligence (AI) Transforming Indian Agriculture - PIB",
      "url": "https://news.google.com/rss/articles/CBMiekFVX3lxTE92VWxMWjh1SDc5R3hic2pJYzl1VDRzN0VOdm9qWHVRN1pDRjdYbzQ3Z3c2WEUtTlJkdGdERnFzU2huam5EX2pjOWJ5UXZfOU9OcFFhMlprUnVxQTRhclJWMVRaNGRPbTVOc3dqanFaMl92SnMtcnVvRkFR?oc=5",
      "description": "<a href=\"https://news.google.com/rss/articles/CBMiekFVX3lxTE92VWxMWjh1SDc5R3hic2pJYzl1VDRzN0VOdm9qWHVRN1pDRjdYbzQ3Z3c2WEUtTlJkdGdERnFzU2huam5EX2pjOWJ5UXZfOU9OcFFhMlprUnVxQTRhclJWMVRaNGRPbTVOc3dqanFaMl92SnMtcnVvRkFR?oc=5\"...",
      "source": "PIB",
      "image": "",
      "lang": "en",
      "pubDate": "2026-07-01T10:27:20.538Z"
    },
    {
      "title": "Union Minister Shri Shivraj Singh Chouhan Leads States in Kharif Campaign 2026 Strategy Meet - PIB",
      "url": "https://news.google.com/rss/articles/CBMiekFVX3lxTFBwM3N2SHBCVkZoWGJvWkdTRVl4SHB1RERLRUxCZHhJaWdDbE02NVFfQ0NRaGd1OTM4cUtkVVZqVTdzN1o3dnAyb1U0ODJfMEhwLVRiOV9IQVJuZ2w3YktDT3BIeF9tTVZvbXhhbkZGM2laTFhOSEppcU5B?oc=5",
      "description": "<a href=\"https://news.google.com/rss/articles/CBMiekFVX3lxTFBwM3N2SHBCVkZoWGJvWkdTRVl4SHB1RERLRUxCZHhJaWdDbE02NVFfQ0NRaGd1OTM4cUtkVVZqVTdzN1o3dnAyb1U0ODJfMEhwLVRiOV9IQVJuZ2w3YktDT3BIeF9tTVZvbXhhbkZGM2laTFhOSEppcU5B?oc=5\"...",
      "source": "PIB",
      "image": "",
      "lang": "en",
      "pubDate": "2026-07-01T10:27:20.538Z"
    },
    {
      "title": "Third Advance Estimates Reflect India’s Agricultural Strength; Union Minister Shri Shivraj Singh Chouhan Approves Record Crop Projections - PIB",
      "url": "https://news.google.com/rss/articles/CBMiekFVX3lxTE9fRTE3RmFiMzcxNzU2dlI1aHpSY3R2eDV4MU9lX0tjaFo4bS1USERoMVktR1I4bGNvdHRKTXEwcS1CYnhobXJIYnp1blQ0SWhVTkRjQk1JeVJwTW1tM09hOVZxRVlzRlM3bmJicjRTOVlaX3JCYndldGJR?oc=5",
      "description": "<a href=\"https://news.google.com/rss/articles/CBMiekFVX3lxTE9fRTE3RmFiMzcxNzU2dlI1aHpSY3R2eDV4MU9lX0tjaFo4bS1USERoMVktR1I4bGNvdHRKTXEwcS1CYnhobXJIYnp1blQ0SWhVTkRjQk1JeVJwTW1tM09hOVZxRVlzRlM3bmJicjRTOVlaX3JCYndldGJR?oc=5\"...",
      "source": "PIB",
      "image": "",
      "lang": "en",
      "pubDate": "2026-07-01T10:27:20.538Z"
    },
    {
      "title": "National Academy of Agricultural Sciences organizes a Brainstorming session to develop a roadmap for achieving Atmanirbharta in fertilizers - PIB",
      "url": "https://news.google.com/rss/articles/CBMiekFVX3lxTFB1UUgwLVYwbjJQTnMyNGNSQWVtWmc4X2hidzk4WnZKTFl0c1RHejZ2R0NrMU9jcS13UTZfd2NKNnNObExQdjkzd1dVeXNJdE83NTk2al93cWFXcHJtbVhGUEE4VV9OS1c0RmNBSzRERjFIQjVoSnpxdUNR?oc=5",
      "description": "<a href=\"https://news.google.com/rss/articles/CBMiekFVX3lxTFB1UUgwLVYwbjJQTnMyNGNSQWVtWmc4X2hidzk4WnZKTFl0c1RHejZ2R0NrMU9jcS13UTZfd2NKNnNObExQdjkzd1dVeXNJdE83NTk2al93cWFXcHJtbVhGUEE4VV9OS1c0RmNBSzRERjFIQjVoSnpxdUNR?oc=5\"...",
      "source": "PIB",
      "image": "",
      "lang": "en",
      "pubDate": "2026-07-01T10:27:20.538Z"
    },
    {
      "title": "India’s Agricultural Transformation: How India’s Agri sector transformed over the last decade - organiser.org",
      "url": "https://news.google.com/rss/articles/CBMi1AFBVV95cUxQb21Hbll0VmpTbERMWG1WTEFrMGFCS3VSWkx2ck9tX2dVVlQ4T29rNHJKT0NQZFNoRm05c0VpY2RoYTFURlIxMHZfaUJUMW1STmhJSWxJcmpZUUNhSlQxM1dDUDBUS0xQRDY2MFN2WWJUaDA2MHB4N3ZJZFlmY0xjU280R1ZhOWN0RzBrMmxwb3NyNjR6QklDVzdtUjlvZjJLT1ZHc192RkhXMm5ta1Nad3h3Z052MUIzNmFCTmszYktPZzhsYTZIT2dlTWlWZzlRLTZTeNIB2gFBVV95cUxNazhKQ0dPQ0dHVDBZSm1pSFppZDREU1ZPTDlJNXM4UnZjWGFHdmFsRUNDb04wZkRHckNCWU8zYlB5TWZyQmpRaDlwRDNHcHI0ZlNnSHZoMmhOVUtGOFlEaVNqR2dFX1REd2pnSUdORWNRb2k2cjVhSzBmQS1pck5ua1U0ZzRXb0t1RFZLX1k2MWsyMmhFYlpXa3Z0LXJXMkwzNXRJVElrbXlMVnFzZVRSdXY3UVN6Y1NnczhpX2JKMjFjMnhJX2hJYy0tTWtzaGo0bGd5V1lsR3FMUQ?oc=5",
      "description": "<a href=\"https://news.google.com/rss/articles/CBMi1AFBVV95cUxQb21Hbll0VmpTbERMWG1WTEFrMGFCS3VSWkx2ck9tX2dVVlQ4T29rNHJKT0NQZFNoRm05c0VpY2RoYTFURlIxMHZfaUJUMW1STmhJSWxJcmpZUUNhSlQxM1dDUDBUS0xQRDY2MFN2WWJUaDA2MHB4N3ZJZFlmY0...",
      "source": "organiser.org",
      "image": "",
      "lang": "en",
      "pubDate": "2026-07-01T10:27:20.538Z"
    }
  ],
  "articles": [
    {
      "title": "जून 2026 में महिंद्रा ट्रैक्टरों की बिक्री 12% बढ़ी, घरेलू बाजार की मजबूत मांग से मिला सहारा",
      "url": "https://www.krishakjagat.org/agriculture-machinery/mahindra-tractor-sales-rose-by-12-in-june-2026-supported-by-strong-domestic-market-demand/",
      "description": "KRISHAK JAGAT | National Agriculture Hindi Newspaper 01 जुलाई 2026, मुंबई: जून 2026 में महिंद्रा ट्रैक्टरों की बिक्री 12% बढ़ी, घरेलू बाजार की मजबूत मांग से मिला सहारा &#8211; महिंद्रा एंड महिंद्रा लिमिटेड के फार्म इक्वि...",
      "source": "Krishak Jagat",
      "image": "https://www.krishakjagat.org/wp-content/uploads/2026/07/Untitled-1-13.jpg",
      "lang": "hi",
      "pubDate": "2026-07-01T10:27:12.172Z"
    },
    {
      "title": "खरीफ 2026: कृषि आदान विक्रेताओं पर कृषि विभाग की सख्ती, 10 नमूने जांच के लिए भेजे",
      "url": "https://www.krishakjagat.org/news/kharif-2026-agriculture-department-cracks-down-on-agri-input-dealers-10-samples-sent-for-testing/",
      "description": "KRISHAK JAGAT | National Agriculture Hindi Newspaper 01 जुलाई 2026, खंडवा: खरीफ 2026: कृषि आदान विक्रेताओं पर कृषि विभाग की सख्ती, 10 नमूने जांच के लिए भेजे &#8211; आगामी खरीफ मौसम 2026 को देखते हुए किसानों को गुणवत्तायु...",
      "source": "Krishak Jagat",
      "image": "https://www.krishakjagat.org/wp-content/uploads/2026/07/wwww.jpg",
      "lang": "hi",
      "pubDate": "2026-07-01T10:27:12.172Z"
    },
    {
      "title": "बाढ़ से तबाह फसलों का लेंगे जायजा, आज अरुणाचल-असम के बाढ़ प्रभावित इलाकों में पहुंचेंगे शिवराज सिंह",
      "url": "https://www.krishakjagat.org/national-news/shivraj-singh-to-assess-flood-ravaged-crops-will-reach-flood-hit-areas-of-arunachal-and-assam-today/",
      "description": "KRISHAK JAGAT | National Agriculture Hindi Newspaper 01 जुलाई 2026, नई दिल्ली: बाढ़ से तबाह फसलों का लेंगे जायजा, आज अरुणाचल-असम के बाढ़ प्रभावित इलाकों में पहुंचेंगे शिवराज सिंह &#8211; केंद्रीय कृषि एवं किसान कल्याण तथ...",
      "source": "Krishak Jagat",
      "image": "https://www.krishakjagat.org/wp-content/uploads/2026/07/Untitled-1-12.jpg",
      "lang": "hi",
      "pubDate": "2026-07-01T10:27:12.172Z"
    },
    {
      "title": "SOMS 2026: स्पेशलिटी फर्टिलाइज़र में आत्मनिर्भरता और नवाचार पर होगा मंथन",
      "url": "https://www.krishakjagat.org/industry-news/soms-2026-deliberations-to-focus-on-self-reliance-and-innovation-in-specialty-fertilizers/",
      "description": "KRISHAK JAGAT | National Agriculture Hindi Newspaper 01 जुलाई 2026, नई दिल्ली: SOMS 2026: स्पेशलिटी फर्टिलाइज़र में आत्मनिर्भरता और नवाचार पर होगा मंथन &#8211; भारत के स्पेशलिटी फर्टिलाइज़र उद्योग को आत्मनिर्भर बनाने और ...",
      "source": "Krishak Jagat",
      "image": "https://www.krishakjagat.org/wp-content/uploads/2026/07/Banner-800x445_20260603_101649_0000-1.jpg",
      "lang": "hi",
      "pubDate": "2026-07-01T10:27:12.172Z"
    },
    {
      "title": "कुक्कुट खाद : कम लागत में उपज बढ़ाने और मिट्टी की सेहत सुधारने का प्रभावी जैविक विकल्प",
      "url": "https://www.krishakjagat.org/news/poultry-manure-an-effective-organic-option-to-boost-yields-and-improve-soil-health-at-a-low-cost/",
      "description": "KRISHAK JAGAT | National Agriculture Hindi Newspaper 01 जुलाई 2026, भोपाल: कुक्कुट खाद : कम लागत में उपज बढ़ाने और मिट्टी की सेहत सुधारने का प्रभावी जैविक विकल्प &#8211; आधुनिक कृषि ने देश में खाद्यान्न उत्पादन बढ़ाने मे...",
      "source": "Krishak Jagat",
      "image": "https://www.krishakjagat.org/wp-content/uploads/2026/07/Untitled-1-11.jpg",
      "lang": "hi",
      "pubDate": "2026-07-01T10:27:12.172Z"
    },
    {
      "title": "सतत कृषि विकास में महिलाओं की भूमिका पर राष्ट्रीय मंथन, पूसा सम्मेलन में जारी हुआ भविष्य का रोडमैप",
      "url": "https://www.krishakjagat.org/national-news/national-deliberation-on-the-role-of-women-in-sustainable-agricultural-development-future-roadmap-unveiled-at-the-pusa-conference/",
      "description": "KRISHAK JAGAT | National Agriculture Hindi Newspaper 01 जुलाई 2026, नई दिल्ली: सतत कृषि विकास में महिलाओं की भूमिका पर राष्ट्रीय मंथन, पूसा सम्मेलन में जारी हुआ भविष्य का रोडमैप &#8211; डॉ. राजेंद्र प्रसाद केंद्रीय कृषि ...",
      "source": "Krishak Jagat",
      "image": "https://www.krishakjagat.org/wp-content/uploads/2026/07/wrrr-1.jpg",
      "lang": "hi",
      "pubDate": "2026-07-01T10:27:12.172Z"
    },
    {
      "title": "रबी सीजन में किसानों को दिन में मिलेगी बिजली, मुख्यमंत्री डॉ. मोहन यादव का बड़ा ऐलान",
      "url": "https://www.krishakjagat.org/news/farmers-to-receive-electricity-during-the-day-in-the-rabi-season-major-announcement-by-chief-minister-dr-mohan-yadav/",
      "description": "KRISHAK JAGAT | National Agriculture Hindi Newspaper 01 जुलाई 2026, भोपाल: रबी सीजन में किसानों को दिन में मिलेगी बिजली, मुख्यमंत्री डॉ. मोहन यादव का बड़ा ऐलान &#8211; मध्यप्रदेश के किसानों के लिए राहत भरी खबर है। मुख्यम...",
      "source": "Krishak Jagat",
      "image": "https://www.krishakjagat.org/wp-content/uploads/2026/07/Untitled-1-10.jpg",
      "lang": "hi",
      "pubDate": "2026-07-01T10:27:12.172Z"
    },
    {
      "title": "आरएचबी बाजरा : कम अवधि में अधिक उत्पादन देने वाली पोषक तत्वों से भरपूर उन्नत किस्म",
      "url": "https://www.krishakjagat.org/crop-cultivation/rhb-bajra-a-nutrient-rich-high-yielding-short-duration-improved-variety/",
      "description": "KRISHAK JAGAT | National Agriculture Hindi Newspaper 01 जुलाई 2026, नई दिल्ली: आरएचबी बाजरा : कम अवधि में अधिक उत्पादन देने वाली पोषक तत्वों से भरपूर उन्नत किस्म &#8211; यदि किसान कम समय में अधिक उपज, बेहतर पोषण गुणवत्ता...",
      "source": "Krishak Jagat",
      "image": "https://www.krishakjagat.org/wp-content/uploads/2026/07/Untitled-1-9.jpg",
      "lang": "hi",
      "pubDate": "2026-07-01T10:27:12.172Z"
    },
    {
      "title": "किसान सारथी : डिजिटल खेती का भरोसेमंद साथी, मिल रही खेती की हर जरूरी जानकारी",
      "url": "https://www.krishakjagat.org/news/kisan-sarathi-a-trusted-companion-for-digital-farming-providing-all-essential-agricultural-information/",
      "description": "KRISHAK JAGAT | National Agriculture Hindi Newspaper 01 जुलाई 2026, भोपाल: किसान सारथी : डिजिटल खेती का भरोसेमंद साथी, मिल रही खेती की हर जरूरी जानकारी &#8211; भारत में कृषि क्षेत्र तेजी से डिजिटल तकनीक को अपनाते हुए आधु...",
      "source": "Krishak Jagat",
      "image": "https://www.krishakjagat.org/wp-content/uploads/2026/07/Untitled-1-8.jpg",
      "lang": "hi",
      "pubDate": "2026-07-01T10:27:12.172Z"
    },
    {
      "title": "खरीफ 2026-27 : किसानों के लिए शुरू हुई ऑनलाइन खाद टोकन बुकिंग, अब लंबी कतारों से मिलेगी राहत",
      "url": "https://www.krishakjagat.org/news/kharif-2026-27-online-fertilizer-token-booking-launched-for-farmers-relief-from-long-queues-now/",
      "description": "KRISHAK JAGAT | National Agriculture Hindi Newspaper 01 जुलाई 2026, भोपाल: खरीफ 2026-27 : किसानों के लिए शुरू हुई ऑनलाइन खाद टोकन बुकिंग, अब लंबी कतारों से मिलेगी राहत &#8211; मध्यप्रदेश के किसानों के लिए राहत भरी खबर है...",
      "source": "Krishak Jagat",
      "image": "https://www.krishakjagat.org/wp-content/uploads/2026/07/Untitled-1-7.jpg",
      "lang": "hi",
      "pubDate": "2026-07-01T10:27:12.172Z"
    },
    {
      "title": "साप्ताहिक मंडी भाव और क्रॉप प्राइस विश्लेषण: अनाज, दालों और तेलहन फसलों के भाव में उतार-चढ़ाव - Tractor Junction",
      "url": "https://news.google.com/rss/articles/CBMimwFBVV95cUxOSnliRVM3ZmlnTXpmS3FldERza0JSM3FFOW1pSHlEdDdYVjVudEN4Sm1LY3NWNEhzbVJ2blJ0VmU5dnBITURQYkw5TnJBa2hQb0o5RmRPRmJCTEx3QVVLcVB2bGlBV0d2N3hUc3kyVDF3SG1GelZzWC05cnk4Rkt4eWdQbHVsckdIWFNnVlFZZWlMajB5dTFucmhKc9IBowFBVV95cUxQRnBFUTF6Mm8xTjF1RGhYcXN5QVJVTlMxdFdtMlFEZEQzQm11RFlGcEtLSHdIVk5CUlpPMF9CZkRuSTN5NGh4OG80dTZVRmlvNzBNbUtlZzJiWVVuWHYwREtlTjd5RUhFMGM1Nkx0Y3QxeHB4LVZYZGtwVFdWOE9KUTVTWjJfMUpJZkhKYmlCVWYwOXoyR25MYjVFMVI3elFvZTZF?oc=5",
      "description": "<a href=\"https://news.google.com/rss/articles/CBMimwFBVV95cUxOSnliRVM3ZmlnTXpmS3FldERza0JSM3FFOW1pSHlEdDdYVjVudEN4Sm1LY3NWNEhzbVJ2blJ0VmU5dnBITURQYkw5TnJBa2hQb0o5RmRPRmJCTEx3QVVLcVB2bGlBV0d2N3hUc3kyVDF3SG1GelZzWC05cnk4Rk...",
      "source": "Tractor Junction",
      "image": "",
      "lang": "hi",
      "pubDate": "2026-07-01T10:27:16.118Z"
    },
    {
      "title": "155261 पर किसान कल से करें कॉल, AI बताएगा मौसम, सरकारी योजनाओं, मंडी भाव, फसल का हाल - ndtv.in",
      "url": "https://news.google.com/rss/articles/CBMixAFBVV95cUxPWnUxRkp2SkpibzdraWdQQWltZEloSjdDbEF6VHZmU1BEcU1BbERJSUI1ZVo1MUlkejVYX3lNY1o5QVpsNTRUSTN1YllaaHdnUS1TQk16aEpMRG0zME1NSkUzY0c4NjNJWlJsOEtCdGpib3phOFlsMENrQzJSMVRuNV92WTllYS1TOEwtRkgweDZfMzFDZFVqQ0wxTzU4N3BYN0MyRFR4ZW1waWJDdVJkYUY1T3ItQllRa1l3M0JWNXhfT3Jm?oc=5",
      "description": "<a href=\"https://news.google.com/rss/articles/CBMixAFBVV95cUxPWnUxRkp2SkpibzdraWdQQWltZEloSjdDbEF6VHZmU1BEcU1BbERJSUI1ZVo1MUlkejVYX3lNY1o5QVpsNTRUSTN1YllaaHdnUS1TQk16aEpMRG0zME1NSkUzY0c4NjNJWlJsOEtCdGpib3phOFlsMENrQzJSMV...",
      "source": "ndtv.in",
      "image": "",
      "lang": "hi",
      "pubDate": "2026-07-01T10:27:16.118Z"
    },
    {
      "title": "5 काम जो किसानों के लिए भारत-विस्तार प्लेटफॉर्म से आसान हो जाएंगे? ये काम कैसे करेगा - News18 Hindi",
      "url": "https://news.google.com/rss/articles/CBMi1AFBVV95cUxPUmhaNnRSQkIzQWtLWDVWaWZzd1FmUURXZFdWNjFyMmVicGpaajYzTXpWaUdXd2dvMHNJNVU5bmhvOG1md3N5SEw5WEVzdEhCR0JnM0stSTFCLTZSVVVCYi05SVo2Ykd0NElQU1AyR2U3NU1uREtpMERlbmgxbVRLOWwyUUR5S2Q5VGFEeldMSjF4WDVoQ2NrTFYtUmxoMmkyWGU1cmpGcGYwUmw0Szl6bXlENkxEUHNSQW1nenptLWFfdWJOckgyWVlqaFAzR3Zmczlqd9IB2gFBVV95cUxObk1Kem5nY1pVbDI3blZWRjR1a2xFQU83NTJoYXJNQ0J5TXZBNEI0QnlfR1V0dVduODN6d2N4XzR5eWdfeW1DR3o3Z21IZUUwd3JPb0NJdm9kcFg1eVFlUFhacmFkZFg1UWh4Z2Q1UWpCUU5Ba21VT2g2TGgzci1uc2xsSFhqMjVwbThKbjRnSGpNRU9rRU05VVE5NU1WcW1tUldsV2JQWWZJWUlSOER6S2lRMU9xOG5QZjJLQ210Uy1wZWwzQXNTQ3dyOGJZWWdKbWx1bUtGLTNIUQ?oc=5",
      "description": "<a href=\"https://news.google.com/rss/articles/CBMi1AFBVV95cUxPUmhaNnRSQkIzQWtLWDVWaWZzd1FmUURXZFdWNjFyMmVicGpaajYzTXpWaUdXd2dvMHNJNVU5bmhvOG1md3N5SEw5WEVzdEhCR0JnM0stSTFCLTZSVVVCYi05SVo2Ykd0NElQU1AyR2U3NU1uREtpMERlbmgxbV...",
      "source": "News18 Hindi",
      "image": "",
      "lang": "hi",
      "pubDate": "2026-07-01T10:27:16.118Z"
    },
    {
      "title": "300 रुपये कुंतल पर आलू 20 रुपये किलो पर बिक्री, उत्तर भारत की मंडियों में औंधे गिरे दाम, लागत निकालने को जूझ रहे किसान - Jansatta",
      "url": "https://news.google.com/rss/articles/CBMizgFBVV95cUxQQnFXTzNfZk1DMTd5dUE3WHByNU9YbnBoSUhzLUplYzVQcld1LU9YUXNIZHNtUHJoSlRTY3JtOXRxVzQwU3BYR2xJcVFlOUt2X282aXBFQXFGRU9mTjhIOHNwckJsUDRmSWxJdXVsMmFyQjVLQWs1eFdrQW9aQk1vTlVTWFpGd3didFRqVU83Y1g1TmdGVGZvMFByenZVUUZyZmNuX2FVck5nNUExQl9ORGszOXlEcXhHdmwzckhnN3ZPNFFCYVBmUjlhLXoxZ9IB1AFBVV95cUxQZGUta2Jnb3VEN3A3WlU0R0l2eWhaNUtrNXNNbVo2Wm5SbWRtTWN6S01IOG5OY250VUZTT0ZqakMya2ZudVgxZ19NLWt0YmpsYTFKdThhMFVpUUs1N0VZNmlkRjllcTBIeFhjT2dnYUY5TjNqT0xvM2dyTTI5NUR3R1RxXzVocWdtUmRTRW0welZFUFBhRWdmajNsa1UwMzJEN2dCQjlIMFZEWktqZEtMWHh6ZGZJRVlleXFkazhMYWVuU3lBREtJX1lMd3hxMmh1WC1Odg?oc=5",
      "description": "<a href=\"https://news.google.com/rss/articles/CBMizgFBVV95cUxQQnFXTzNfZk1DMTd5dUE3WHByNU9YbnBoSUhzLUplYzVQcld1LU9YUXNIZHNtUHJoSlRTY3JtOXRxVzQwU3BYR2xJcVFlOUt2X282aXBFQXFGRU9mTjhIOHNwckJsUDRmSWxJdXVsMmFyQjVLQWs1eFdrQW9aQk...",
      "source": "Jansatta",
      "image": "",
      "lang": "hi",
      "pubDate": "2026-07-01T10:27:16.118Z"
    },
    {
      "title": "Explained: अब AI से खेती का होगा समाधान, किसानों के लिए 'भारत-विस्तार' लॉन्च, जानिए क्या - क्या होंगे काम - Mint",
      "url": "https://news.google.com/rss/articles/CBMi3AFBVV95cUxNWUFMYWlLUzdjeDY0V0hlWkhHLTFjVmdIVDdMNV9WRzhsNEdaS3FZdDZjYjJjcHRVQTZzWHh2XzBsaDJ5bDJyZFVjdlZaZEdnT2xaWEgxNUxKV3ZsdEd4SFIxLTJaQUlKdVgtWHFmZFlIcDBhMEpRSlBpVUx2WHNqOTdpN3g1emE2Sk1qUWViYVFiMXdBaHJwQV9rZ090d2pEYm96NVhudVNldVhJWDY4Nkg0Rkp3Ql93R1pOU3VxSFNKOEpnNUp5clk5SGpYVV9VQU9Uc1c3TnlxZkVR0gHiAUFVX3lxTE00UXdZem5zNm03bU9DZjNNQkg3RGJMaG1yLXBjbTNEWmo1Y1lYMnRoN1N1NUttcGUxQ0RPMmxrVFFNYzZodlc3enVpU2tFamVyOTJGOFkxbVEtYnpiYUdEbHhUbU5PU0ZVSEdNTU1OVV9STGJCSHMwRFREdk1PYS1GX1M5bnc1U0lra0NQaEZwVFN3dFJuY2VaTlRnV1pLa0xJdHNzbkI1aFBiU2hfV0Fub2ZNbkk0S0o3Vm1QUFlEZXZjcVA5TmRtd2xTcDl1UGlIWUEwb1FhUkUtME80aHNscVE?oc=5",
      "description": "<a href=\"https://news.google.com/rss/articles/CBMi3AFBVV95cUxNWUFMYWlLUzdjeDY0V0hlWkhHLTFjVmdIVDdMNV9WRzhsNEdaS3FZdDZjYjJjcHRVQTZzWHh2XzBsaDJ5bDJyZFVjdlZaZEdnT2xaWEgxNUxKV3ZsdEd4SFIxLTJaQUlKdVgtWHFmZFlIcDBhMEpRSlBpVUx2WH...",
      "source": "Mint",
      "image": "",
      "lang": "hi",
      "pubDate": "2026-07-01T10:27:16.118Z"
    }
  ]
}