{
  "updated": "2026-04-22T06:27:16.528Z",
  "count": 30,
  "hi_articles": [
    {
      "title": "मध्यप्रदेश पुलिस का बड़ा अभियान, कई जिलों में छापेमारी कर 178 गौवंश मुक्त; आरोपियों पर कार्रवाई",
      "url": "https://www.krishakjagat.org/news/major-operation-by-madhya-pradesh-police-178-cattle-rescued-in-raids-across-several-districts-action-taken-against-accused/",
      "description": "KRISHAK JAGAT | National Agriculture Hindi Newspaper 22 अप्रैल 2026, भोपाल: मध्यप्रदेश पुलिस का बड़ा अभियान, कई जिलों में छापेमारी कर 178 गौवंश मुक्त; आरोपियों पर कार्रवाई &#8211; मध्यप्रदेश पुलिस ने प्रदेशभर में अवैध गौ...",
      "source": "Krishak Jagat",
      "image": "https://www.krishakjagat.org/wp-content/uploads/2026/04/Untitled-1-321.jpg",
      "lang": "hi",
      "pubDate": "2026-04-22T06:26:46.994Z"
    },
    {
      "title": "मध्यप्रदेश में गेहूं खरीदी तेज: अब तक 1.88 लाख किसानों से 81.76 लाख क्विंटल उपार्जन, 1083 करोड़ भुगतान",
      "url": "https://www.krishakjagat.org/news/wheat-procurement-accelerates-in-madhya-pradesh-81-76-lakh-quintals-procured-from-1-88-lakh-farmers-so-far-%e2%82%b91083-crore-paid/",
      "description": "KRISHAK JAGAT | National Agriculture Hindi Newspaper 22 अप्रैल 2026, भोपाल: मध्यप्रदेश में गेहूं खरीदी तेज: अब तक 1.88 लाख किसानों से 81.76 लाख क्विंटल उपार्जन, 1083 करोड़ भुगतान &#8211; मध्यप्रदेश के खाद्य, नागरिक आपूर्...",
      "source": "Krishak Jagat",
      "image": "https://www.krishakjagat.org/wp-content/uploads/2026/04/liioi.jpg",
      "lang": "hi",
      "pubDate": "2026-04-22T06:26:46.994Z"
    },
    {
      "title": "आज का धान मंडी रेट (21 अप्रैल 2026)",
      "url": "https://www.krishakjagat.org/mandi-rate/todays-paddy-market-rates-april-21-2026/",
      "description": "KRISHAK JAGAT | National Agriculture Hindi Newspaper 21 अप्रैल 2026, नई दिल्ली: आज का धान मंडी रेट (21 अप्रैल 2026) – नीचे दी गई तालिका में पूरे भारत में धान की मंडी दरें हैं। इसमें धान की न्यूनतम, अधिकतम और मोडल दर का उ...",
      "source": "Krishak Jagat",
      "image": "https://www.krishakjagat.org/wp-content/uploads/2026/04/Untitled-1-316.jpg",
      "lang": "hi",
      "pubDate": "2026-04-22T06:26:46.994Z"
    },
    {
      "title": "मध्यप्रदेश: रतलाम में नरवाई प्रबंधन अभियान तेज, 300 किसानों को डीकंपोजर वितरण, खेतों में दिया गया लाइव डेमो",
      "url": "https://www.krishakjagat.org/news/madhya-pradesh-stubble-management-campaign-intensifies-in-ratlam-decomposers-distributed-to-300-farmers-live-demonstrations-conducted-in-fields/",
      "description": "KRISHAK JAGAT | National Agriculture Hindi Newspaper 21 अप्रैल 2026, रतलाम: मध्यप्रदेश: रतलाम में नरवाई प्रबंधन अभियान तेज, 300 किसानों को डीकंपोजर वितरण, खेतों में दिया गया लाइव डेमो &#8211; मध्यप्रदेश के रतलाम जिले में...",
      "source": "Krishak Jagat",
      "image": "https://www.krishakjagat.org/wp-content/uploads/2026/04/Untitled-1-320.jpg",
      "lang": "hi",
      "pubDate": "2026-04-22T06:26:46.994Z"
    },
    {
      "title": "Success Story: PRO की नौकरी छोड़ किसान बने राहुल, अब 10 एकड़ में अश्वगंधा उगाकर कमा रहे लाखों",
      "url": "https://www.krishakjagat.org/news/success-story-rahul-quits-pro-job-to-become-a-farmer-now-earns-lakhs-by-cultivating-ashwagandha-on-10-acres/",
      "description": "KRISHAK JAGAT | National Agriculture Hindi Newspaper 21 अप्रैल 2026, भोपाल: Success Story: PRO की नौकरी छोड़ किसान बने राहुल, अब 10 एकड़ में अश्वगंधा उगाकर कमा रहे लाखों &#8211; मध्य प्रदेश के सागर जिले के देवरी विकासखंड...",
      "source": "Krishak Jagat",
      "image": "https://www.krishakjagat.org/wp-content/uploads/2026/04/Untitled-1-319.jpg",
      "lang": "hi",
      "pubDate": "2026-04-22T06:26:46.994Z"
    },
    {
      "title": "IMD Bhopal Alert: मध्य प्रदेश में तेज गर्मी का कहर, खजुराहो में 43°C पहुंचा पारा; IMD ने जारी किया अलर्ट",
      "url": "https://www.krishakjagat.org/news/imd-bhopal-alert-intense-heatwave-grips-madhya-pradesh-mercury-hits-43c-in-khajuraho-imd-issues-alert/",
      "description": "KRISHAK JAGAT | National Agriculture Hindi Newspaper 21 अप्रैल 2026, भोपाल: IMD Bhopal Alert: मध्य प्रदेश में तेज गर्मी का कहर, खजुराहो में 43°C पहुंचा पारा; IMD ने जारी किया अलर्ट &#8211; मध्य प्रदेश में मौसम का मिजाज त...",
      "source": "Krishak Jagat",
      "image": "https://www.krishakjagat.org/wp-content/uploads/2026/04/Untitled-1-317.jpg",
      "lang": "hi",
      "pubDate": "2026-04-22T06:26:46.994Z"
    },
    {
      "title": "Weather Update: देश में मौसम का डबल अटैक, 44°C की लू के बीच कई राज्यों में तूफानी बारिश का अलर्ट; IMD ने दी चेतावनी",
      "url": "https://www.krishakjagat.org/national-news/weather-update-double-whammy-for-the-nation-stormy-rain-alert-issued-for-several-states-amidst-44c-heatwave-imd-issues-warning/",
      "description": "KRISHAK JAGAT | National Agriculture Hindi Newspaper 21 अप्रैल 2026, नई दिल्ली: Weather Update: देश में मौसम का डबल अटैक, 44°C की लू के बीच कई राज्यों में तूफानी बारिश का अलर्ट; IMD ने दी चेतावनी &#8211; भारतीय मौसम विज्...",
      "source": "Krishak Jagat",
      "image": "https://www.krishakjagat.org/wp-content/uploads/2026/04/Untitled-1-313.jpg",
      "lang": "hi",
      "pubDate": "2026-04-22T06:26:46.994Z"
    },
    {
      "title": "Wheat Export: सरकार का बड़ा फैसला, 25 लाख टन अतिरिक्त गेहूं निर्यात को मंजूरी, किसानों को मिलेगा फायदा",
      "url": "https://www.krishakjagat.org/national-news/wheat-exports-major-government-decision-approval-granted-for-export-of-2-5-million-tonnes-of-additional-wheat-farmers-to-benefit/",
      "description": "KRISHAK JAGAT | National Agriculture Hindi Newspaper 21 अप्रैल 2026, नई दिल्ली: Wheat Export: सरकार का बड़ा फैसला, 25 लाख टन अतिरिक्त गेहूं निर्यात को मंजूरी, किसानों को मिलेगा फायदा &#8211; भारत सरकार ने अतिरिक्त 25 लाख...",
      "source": "Krishak Jagat",
      "image": "https://www.krishakjagat.org/wp-content/uploads/2026/04/Untitled-1-312.jpg",
      "lang": "hi",
      "pubDate": "2026-04-22T06:26:46.994Z"
    },
    {
      "title": "ग्रीष्मकालीन फसलों का बढ़ा रकबा, 69.06 लाख हेक्टेयर तक पहुंची बुवाई; दलहन और मोटे अनाज में भी तेजी",
      "url": "https://www.krishakjagat.org/national-news/area-under-summer-crops-expands-sowing-reaches-69-06-lakh-hectares-with-a-surge-in-pulses-and-coarse-cereals-as-well/",
      "description": "KRISHAK JAGAT | National Agriculture Hindi Newspaper 21 अप्रैल 2026, नई दिल्ली: ग्रीष्मकालीन फसलों का बढ़ा रकबा, 69.06 लाख हेक्टेयर तक पहुंची बुवाई; दलहन और मोटे अनाज में भी तेजी &#8211; कृषि एवं किसान कल्याण मंत्रालय के...",
      "source": "Krishak Jagat",
      "image": "https://www.krishakjagat.org/wp-content/uploads/2026/04/Untitled-1-311.jpg",
      "lang": "hi",
      "pubDate": "2026-04-22T06:26:46.994Z"
    },
    {
      "title": "टिंडा की फसल पर मंडराया डाउनी मिल्ड्यू का खतरा, किसान ऐसे करें तुरंत बचाव",
      "url": "https://www.krishakjagat.org/crop-cultivation/threat-of-downy-mildew-looms-over-tinda-crop-farmers-should-take-immediate-preventive-measures/",
      "description": "KRISHAK JAGAT | National Agriculture Hindi Newspaper 21 अप्रैल 2026, नई दिल्ली: टिंडा की फसल पर मंडराया डाउनी मिल्ड्यू का खतरा, किसान ऐसे करें तुरंत बचाव &#8211; टिंडा (राउण्ड गार्ड) की फसल में इन दिनों पत्तियों के पीले ...",
      "source": "Krishak Jagat",
      "image": "https://www.krishakjagat.org/wp-content/uploads/2026/04/Untitled-1-310.jpg",
      "lang": "hi",
      "pubDate": "2026-04-22T06:26:46.994Z"
    },
    {
      "title": "साप्ताहिक मंडी भाव और क्रॉप प्राइस विश्लेषण: अनाज, दालों और तेलहन फसलों के भाव में उतार-चढ़ाव - Tractor Junction",
      "url": "https://news.google.com/rss/articles/CBMimwFBVV95cUxOSnliRVM3ZmlnTXpmS3FldERza0JSM3FFOW1pSHlEdDdYVjVudEN4Sm1LY3NWNEhzbVJ2blJ0VmU5dnBITURQYkw5TnJBa2hQb0o5RmRPRmJCTEx3QVVLcVB2bGlBV0d2N3hUc3kyVDF3SG1GelZzWC05cnk4Rkt4eWdQbHVsckdIWFNnVlFZZWlMajB5dTFucmhKc9IBowFBVV95cUxQRnBFUTF6Mm8xTjF1RGhYcXN5QVJVTlMxdFdtMlFEZEQzQm11RFlGcEtLSHdIVk5CUlpPMF9CZkRuSTN5NGh4OG80dTZVRmlvNzBNbUtlZzJiWVVuWHYwREtlTjd5RUhFMGM1Nkx0Y3QxeHB4LVZYZGtwVFdWOE9KUTVTWjJfMUpJZkhKYmlCVWYwOXoyR25MYjVFMVI3elFvZTZF?oc=5",
      "description": "<a href=\"https://news.google.com/rss/articles/CBMimwFBVV95cUxOSnliRVM3ZmlnTXpmS3FldERza0JSM3FFOW1pSHlEdDdYVjVudEN4Sm1LY3NWNEhzbVJ2blJ0VmU5dnBITURQYkw5TnJBa2hQb0o5RmRPRmJCTEx3QVVLcVB2bGlBV0d2N3hUc3kyVDF3SG1GelZzWC05cnk4Rk...",
      "source": "Tractor Junction",
      "image": "",
      "lang": "hi",
      "pubDate": "2026-04-22T06:26:51.886Z"
    },
    {
      "title": "सरसों किसानों की हुई बल्ले-बल्ले, MSP से ज्यादा हुआ मंडी भाव...ईरान-अमेर‍िका युद्ध से बाजार में तेजी - Kisan Tak",
      "url": "https://news.google.com/rss/articles/CBMizAFBVV95cUxQb0dXUGh3NWlidEVKNVNOQ3poVkFJRVZFT2hRZFNVUXVERFltaHBEeEZtcVlhblhYNjBoaG9UejczLWJDcXJrSWFIV0Rna3hwN3lyZE01VklRUnV6bDFjTEZYN1E5LUtXNHNVRms4YlFpTXdFUGFhUmxoTWJIelpyWXcwWnZSQ1FjWmxlRFF1OFhUMGlvSlY0Nndmc0g1S1ozTnl4OHhYbHZTdW9zT0dERlJHVWxybVBRN1RtNzBacUpTYzZaR1MxdUhTcjPSAdIBQVVfeXFMTS1wV1lGa3hsd1VEbGZGSVhDZFBpUG45UWRFYXdDR0U1QXF5RDZ6RUJZQkpXUzNIcUpGRzZwQ2sybjhzOGVadHNvYUstaGxXNzEySWlrVm84Y3FrdkFMQjMyRkYtMUpES3otcnd3amdVMnVyWWd6U1NJZnJXV0dNMkpNSS1uQ3ZzZTQtVmtEWjlXUF9KdlBGNzl4dHNRbVczaWc3UTBWRVV6dmdYWTZwOW1Qb09LRlFLamdmX1VsU1UyeEg3V2FfcmVCeV9kaWM1OExR?oc=5",
      "description": "<a href=\"https://news.google.com/rss/articles/CBMizAFBVV95cUxQb0dXUGh3NWlidEVKNVNOQ3poVkFJRVZFT2hRZFNVUXVERFltaHBEeEZtcVlhblhYNjBoaG9UejczLWJDcXJrSWFIV0Rna3hwN3lyZE01VklRUnV6bDFjTEZYN1E5LUtXNHNVRms4YlFpTXdFUGFhUmxoTWJIel...",
      "source": "Kisan Tak",
      "image": "",
      "lang": "hi",
      "pubDate": "2026-04-22T06:26:51.887Z"
    },
    {
      "title": "5 काम जो किसानों के लिए भारत-विस्तार प्लेटफॉर्म से आसान हो जाएंगे? ये काम कैसे करेगा - News18 Hindi",
      "url": "https://news.google.com/rss/articles/CBMi1AFBVV95cUxPUmhaNnRSQkIzQWtLWDVWaWZzd1FmUURXZFdWNjFyMmVicGpaajYzTXpWaUdXd2dvMHNJNVU5bmhvOG1md3N5SEw5WEVzdEhCR0JnM0stSTFCLTZSVVVCYi05SVo2Ykd0NElQU1AyR2U3NU1uREtpMERlbmgxbVRLOWwyUUR5S2Q5VGFEeldMSjF4WDVoQ2NrTFYtUmxoMmkyWGU1cmpGcGYwUmw0Szl6bXlENkxEUHNSQW1nenptLWFfdWJOckgyWVlqaFAzR3Zmczlqd9IB2gFBVV95cUxObk1Kem5nY1pVbDI3blZWRjR1a2xFQU83NTJoYXJNQ0J5TXZBNEI0QnlfR1V0dVduODN6d2N4XzR5eWdfeW1DR3o3Z21IZUUwd3JPb0NJdm9kcFg1eVFlUFhacmFkZFg1UWh4Z2Q1UWpCUU5Ba21VT2g2TGgzci1uc2xsSFhqMjVwbThKbjRnSGpNRU9rRU05VVE5NU1WcW1tUldsV2JQWWZJWUlSOER6S2lRMU9xOG5QZjJLQ210Uy1wZWwzQXNTQ3dyOGJZWWdKbWx1bUtGLTNIUQ?oc=5",
      "description": "<a href=\"https://news.google.com/rss/articles/CBMi1AFBVV95cUxPUmhaNnRSQkIzQWtLWDVWaWZzd1FmUURXZFdWNjFyMmVicGpaajYzTXpWaUdXd2dvMHNJNVU5bmhvOG1md3N5SEw5WEVzdEhCR0JnM0stSTFCLTZSVVVCYi05SVo2Ykd0NElQU1AyR2U3NU1uREtpMERlbmgxbV...",
      "source": "News18 Hindi",
      "image": "",
      "lang": "hi",
      "pubDate": "2026-04-22T06:26:51.887Z"
    },
    {
      "title": "Mandi News: किसानों की बल्ले-बल्ले, सरसों का भाव 6850 रुपए तक पहुंचा, जानें मंडी रेट - Patrika News",
      "url": "https://news.google.com/rss/articles/CBMisgFBVV95cUxQVjVxR1JGZFN0RnE5azJ5Z1VLTE0xZG1FYjA0Vnc5ZkhvWVpKVVhKRzQ2VVl3NVJPblBCQlM4RXhXWU5ZM1FBTlA3Ty1pZjI2aTJ0YmhRMGV6UzJMNW9vZUlGY0RpQjByRTdhSTg4dW5ZQ0xpX3I1S0xscDVIMlRHZEVsNllvYWxleFZCU0tQNGpxSFJDM2N5dEs0YndrYTJ6SDNPUUdBcTFrYkFxQ1RxM3FB0gG3AUFVX3lxTE1fM2VwMm8xV1MweEtNOTh5VHF5XzB5NG9HVHB6dDVrMEJhWWhNVU5CXzN6ZWowMjc4NVVwQndqTjdLamc3YlRUV1cyT1Zlc3FnTTgxX19kcWthTnUxX2VhR1FDNkJlRldYVlQ3MFJqbU56LW1jLVFQMVU4R2YySEF3cDBFWkxEdnlsbzlkSHF1T05GVTgyRUtOdDFoUV9qS19Yak54cDE1R0F6R1RRcDE0YjVqdXNXRQ?oc=5",
      "description": "<a href=\"https://news.google.com/rss/articles/CBMisgFBVV95cUxQVjVxR1JGZFN0RnE5azJ5Z1VLTE0xZG1FYjA0Vnc5ZkhvWVpKVVhKRzQ2VVl3NVJPblBCQlM4RXhXWU5ZM1FBTlA3Ty1pZjI2aTJ0YmhRMGV6UzJMNW9vZUlGY0RpQjByRTdhSTg4dW5ZQ0xpX3I1S0xscDVIMl...",
      "source": "Patrika News",
      "image": "",
      "lang": "hi",
      "pubDate": "2026-04-22T06:26:51.887Z"
    },
    {
      "title": "155261 पर किसान कल से करें कॉल, AI बताएगा मौसम, सरकारी योजनाओं, मंडी भाव, फसल का हाल - NDTV.in",
      "url": "https://news.google.com/rss/articles/CBMixAFBVV95cUxPWnUxRkp2SkpibzdraWdQQWltZEloSjdDbEF6VHZmU1BEcU1BbERJSUI1ZVo1MUlkejVYX3lNY1o5QVpsNTRUSTN1YllaaHdnUS1TQk16aEpMRG0zME1NSkUzY0c4NjNJWlJsOEtCdGpib3phOFlsMENrQzJSMVRuNV92WTllYS1TOEwtRkgweDZfMzFDZFVqQ0wxTzU4N3BYN0MyRFR4ZW1waWJDdVJkYUY1T3ItQllRa1l3M0JWNXhfT3Jm0gHMAUFVX3lxTE9ySG5ubUJGZnJjZE9KTzNMSFdHa3RZT0VxQ01sM0wwOGdKbjlLd3BaN0Q1SHR4NEFwWEh0dm5VMHJfRWE1bXQ4UE00UHNOU2t2NE1TaHp4UERUMzd6RnVPOTB5aXh5c0s1SkZQZHFrbkE2eFhsbEc5dG5USUVIOFMxTW9JV2pZQmgxNFBzeGNHLTl3OTgyTlJCQlltS2tXejRzbUpBUFhCVTNDc25hN3dxanNULUdtc25lUmU4NlBsMFVWVU9NMkRYbXJ1Zg?oc=5",
      "description": "<a href=\"https://news.google.com/rss/articles/CBMixAFBVV95cUxPWnUxRkp2SkpibzdraWdQQWltZEloSjdDbEF6VHZmU1BEcU1BbERJSUI1ZVo1MUlkejVYX3lNY1o5QVpsNTRUSTN1YllaaHdnUS1TQk16aEpMRG0zME1NSkUzY0c4NjNJWlJsOEtCdGpib3phOFlsMENrQzJSMV...",
      "source": "NDTV.in",
      "image": "",
      "lang": "hi",
      "pubDate": "2026-04-22T06:26:51.887Z"
    }
  ],
  "en_articles": [
    {
      "title": "How natural farming is transforming food production in southern India - UNEP - UN Environment Programme",
      "url": "https://news.google.com/rss/articles/CBMiqwFBVV95cUxORlJfNzlzNzJPU1gxVExwSnNXZkVwaktXcktDNndaUVFHMW5yRk52VEFWbUZQTTBPSXpVOHh4by1rc1d2TklxRHhTYWlNdFVWemhUbFFuTVM4eXdicjhXaVBGNDlRLTQ3QmhWY3hscjVXd3A4TnFvMHZwSHZVMlZGelV1ZDg3Y3RuN1A4dGw4TG9WcVVnNTI0R01hNTlEcExxMEFYcnBqV2x0eHc?oc=5",
      "description": "<a href=\"https://news.google.com/rss/articles/CBMiqwFBVV95cUxORlJfNzlzNzJPU1gxVExwSnNXZkVwaktXcktDNndaUVFHMW5yRk52VEFWbUZQTTBPSXpVOHh4by1rc1d2TklxRHhTYWlNdFVWemhUbFFuTVM4eXdicjhXaVBGNDlRLTQ3QmhWY3hscjVXd3A4TnFvMHZwSHZVMl...",
      "source": "UNEP - UN Environment Programme",
      "image": "",
      "lang": "en",
      "pubDate": "2026-04-22T06:26:56.913Z"
    },
    {
      "title": "El Niño Could Reshape India’s Herbicide Market in 2026. Is the Crop Protection Industry Ready? - Global Agriculture",
      "url": "https://news.google.com/rss/articles/CBMi2wFBVV95cUxQdzJ1cHdDcWpYNDMyRnZRUjJZZG1ySHZja3hnUG9UYXZybExGb29iNWlvY200RWRyM2c5VmREQkExVDNjNjAtLUExcFFSRFVkaWdEeU9XUkxycVRUZGxRR3o3eC1rbTAwcUEwT3VjRmxnZkJ5N3dxX014ZjR1Q0ZOUlRnVlNwVlRXaVVmcEhCMmJWRWNQQXBWamtZemYtTTBQYXAwUzBBc1hrc1VYY0ZXRTd1bWE2a2w5NjRQNlFxTkgzNGVocklZMGV3Z1BMbGdYb3Q1S1o0enpLWVE?oc=5",
      "description": "<a href=\"https://news.google.com/rss/articles/CBMi2wFBVV95cUxQdzJ1cHdDcWpYNDMyRnZRUjJZZG1ySHZja3hnUG9UYXZybExGb29iNWlvY200RWRyM2c5VmREQkExVDNjNjAtLUExcFFSRFVkaWdEeU9XUkxycVRUZGxRR3o3eC1rbTAwcUEwT3VjRmxnZkJ5N3dxX014ZjR1Q0...",
      "source": "Global Agriculture",
      "image": "",
      "lang": "en",
      "pubDate": "2026-04-22T06:26:56.913Z"
    },
    {
      "title": "Accelerating India’s High Value Crop Diversification: From Coastal Plantations to Himalayan Nut Crops - Hindudayashankar",
      "url": "https://news.google.com/rss/articles/CBMi1gFBVV95cUxNakowZkJTQXhOQ0lPOUdGQjNjUFdLdGZ0VmJKX1lVWDR3enF6NU5aWUFOaV9CV05hdzc4aERpMVBydE9rMzA5ZzF0djM0NThxb19yQ2tHVGlxaUVIWThITmZ2eERaNVU5MGZqcXMzMG5CcXI4T1ptNEdDNk92NG9LWk55VDNKSHNxWWh4dzFmMUJucVhyMG5wbTJSaDZrMDhIT0E1YUpqaVdOYWUwM0FxQzkwY0h1TzFhSDdkVDZubWQzbWtDRFJqRVUxRVFtVERTNnEzM1FR?oc=5",
      "description": "<a href=\"https://news.google.com/rss/articles/CBMi1gFBVV95cUxNakowZkJTQXhOQ0lPOUdGQjNjUFdLdGZ0VmJKX1lVWDR3enF6NU5aWUFOaV9CV05hdzc4aERpMVBydE9rMzA5ZzF0djM0NThxb19yQ2tHVGlxaUVIWThITmZ2eERaNVU5MGZqcXMzMG5CcXI4T1ptNEdDNk92NG...",
      "source": "Hindudayashankar",
      "image": "",
      "lang": "en",
      "pubDate": "2026-04-22T06:26:56.913Z"
    },
    {
      "title": "Jaipur Western Regional Agri Conference Marks New Phase in India’s Agricultural Reform Drive - HospiBuz",
      "url": "https://news.google.com/rss/articles/CBMi0wFBVV95cUxQdzE4SDF5NzZjQXl5dHFySXFaek9SSHNDejNUNjdDVE5rNTYwLURZNTlwSUl0clI5MjdaNGVRekhZUVlLbnprU1Nwb25pRmJEQy1GeTItaEVIMFQ3VGsyaHl5Wmh2c043bEduUkZET1Vud3lkamUza0N6YzlyTU1KNmszOXkyeW5sYkVjT045d2o0UHZPUlIwdUVjRWRlNzM1WURmcE5STFJMYUdVQ3lUVGJIdlpKYVkxd3J2YVd4ZEx6MlU1ZWVYTXVZX0xzbkU4UVVv0gHTAUFVX3lxTFB3MThIMXk3NmNBeXl0cXJJcVp6T1JIc0N6M1Q2N0NUTms1NjAtRFk1OXBJSXRyUjkyN1o0ZVF6SFlRWUtuemtTU3BvbmlGYkRDLUZ5Mi1oRUgwVDdUazJoeXlaaHZzTjdsR25SRkRPVW53eWRqZTNrQ3pjOXJNTUo2azM5eTJ5bmxiRWNPTjl3ajRQdk9SUjB1RWNFZGU3MzVZRGZwTlJMUkxhR1VDeVRUYkh2WkphWTF3cnZhV3hkTHoyVTVlZVhNdVlfTHNuRThRVW8?oc=5",
      "description": "<a href=\"https://news.google.com/rss/articles/CBMi0wFBVV95cUxQdzE4SDF5NzZjQXl5dHFySXFaek9SSHNDejNUNjdDVE5rNTYwLURZNTlwSUl0clI5MjdaNGVRekhZUVlLbnprU1Nwb25pRmJEQy1GeTItaEVIMFQ3VGsyaHl5Wmh2c043bEduUkZET1Vud3lkamUza0N6YzlyTU...",
      "source": "HospiBuz",
      "image": "",
      "lang": "en",
      "pubDate": "2026-04-22T06:26:56.913Z"
    },
    {
      "title": "‘It all depends on the crop’: Gulf crisis hits South Asia farmers - Al Jazeera",
      "url": "https://news.google.com/rss/articles/CBMiqAFBVV95cUxOaHVSM2lHR1JUY0Vxalg0QlQ0MnEwbDdKZHlzaFNwaDFPb2F3dmVSMERHcXpBTEkyRmVnMUxJMXFFOGNacU0zci14U2VlMUliU1NpbWZuZ3ZsdkhmSko1N0tDUlI5aS1JTVBRVjJLZXNaX1VuQ2F5Q2ZGMEppb1A0aG0tX3VtV0lnaVR4aDQzRWV6SVlQZVhWQ2kwU1FLSWk4cFQwRVBPSlHSAa4BQVVfeXFMTlFfbG51aTJuYWtyZ3ZmSzB0cnl5WmgyeHRScnZPVjFWVUF6MXRUWjBlbWs3Sks4bUJCQzhkZVc3M2syUXJYVDZMR2JfSXNrVHBTMHRyQU14OXoyQmtwYm55ZkJjRkFIaElTYTY4NnZseEhUMnpKNWttQ2NxOExwOEtlejI3aExRLVRoQnlwenIwX1FJaDByMTNRUTVHMk1qbTd6ek4yc1RHZU5vY1NB?oc=5",
      "description": "<a href=\"https://news.google.com/rss/articles/CBMiqAFBVV95cUxOaHVSM2lHR1JUY0Vxalg0QlQ0MnEwbDdKZHlzaFNwaDFPb2F3dmVSMERHcXpBTEkyRmVnMUxJMXFFOGNacU0zci14U2VlMUliU1NpbWZuZ3ZsdkhmSko1N0tDUlI5aS1JTVBRVjJLZXNaX1VuQ2F5Q2ZGMEppb1...",
      "source": "Al Jazeera",
      "image": "",
      "lang": "en",
      "pubDate": "2026-04-22T06:26:56.913Z"
    },
    {
      "title": "‘India is going to face a food crisis’: Farmers panic over fertiliser shortages amid Iran war - The Guardian",
      "url": "https://news.google.com/rss/articles/CBMilgFBVV95cUxOYURkakJhTDRNSnRua20xcVR6QWY5UWlNSnRHV21oS3Jhb2FGTFVhRmozOFZNTlZjNVRrLXlpdzdLMEFpMlhkWngxSEJLQnFlb2ppSEc1bi1FTlNTMTlCRmNyeHRUQ1NfUEpubHJJTXhrRG5vU3d0LWY3NDdrdW42LVR2aHJ5X1dkRVgxTGRldVZLUVNKNEE?oc=5",
      "description": "<a href=\"https://news.google.com/rss/articles/CBMilgFBVV95cUxOYURkakJhTDRNSnRua20xcVR6QWY5UWlNSnRHV21oS3Jhb2FGTFVhRmozOFZNTlZjNVRrLXlpdzdLMEFpMlhkWngxSEJLQnFlb2ppSEc1bi1FTlNTMTlCRmNyeHRUQ1NfUEpubHJJTXhrRG5vU3d0LWY3NDdrdW...",
      "source": "The Guardian",
      "image": "",
      "lang": "en",
      "pubDate": "2026-04-22T06:26:56.913Z"
    },
    {
      "title": "How Women Came to Make Up Nearly 50% of India’s Agriculture Students - The Better India",
      "url": "https://news.google.com/rss/articles/CBMixgFBVV95cUxPYTZ1cjVodHU3NWc3YldfUDI2QVp0MXc5RUJMNGpyOWRTMUl0X1BTTU13X0ZpTGw4cWJvTnp3UTd3cDY5T3ktdkg0MGNkWDBZeE9lN1NXeHlHNGZDbkI1SFYxQUltSDJxSGwwSk82ZHltQzNfY3lSQkZEMnNINFRIYmNxeWZFeFNaTUdHY0RuTGRGVi0xMm9LMlBMOTJsNEVNcHI1QjJmRXZ3NlV6ZHRqSjY4ZFNfUUZKVndTNXNMMGxGb3VLRVE?oc=5",
      "description": "<a href=\"https://news.google.com/rss/articles/CBMixgFBVV95cUxPYTZ1cjVodHU3NWc3YldfUDI2QVp0MXc5RUJMNGpyOWRTMUl0X1BTTU13X0ZpTGw4cWJvTnp3UTd3cDY5T3ktdkg0MGNkWDBZeE9lN1NXeHlHNGZDbkI1SFYxQUltSDJxSGwwSk82ZHltQzNfY3lSQkZEMnNINF...",
      "source": "The Better India",
      "image": "",
      "lang": "en",
      "pubDate": "2026-04-22T06:26:56.913Z"
    },
    {
      "title": "Centre approves crop procurement relief for farmers in three states - newsage.in",
      "url": "https://news.google.com/rss/articles/CBMibkFVX3lxTE5sajcxTXR5blRwUjc0alJTdG9lU0FtcGhBM2tVbjU1aVpYVEtRdlFDWVU0SEVVeHBPS2ZkMzhYWThyUVdsOER4SWtIV0JCVlBhb2lpb01SNDRGWFNaWEF2V1hNVWEwRVJPVXlTWktR?oc=5",
      "description": "<a href=\"https://news.google.com/rss/articles/CBMibkFVX3lxTE5sajcxTXR5blRwUjc0alJTdG9lU0FtcGhBM2tVbjU1aVpYVEtRdlFDWVU0SEVVeHBPS2ZkMzhYWThyUVdsOER4SWtIV0JCVlBhb2lpb01SNDRGWFNaWEF2V1hNVWEwRVJPVXlTWktR?oc=5\" target=\"_blank\"...",
      "source": "newsage.in",
      "image": "",
      "lang": "en",
      "pubDate": "2026-04-22T06:26:56.913Z"
    },
    {
      "title": "India’s Next Agricultural Revolution Will Be AI-Driven: Dr. Jitendra Singh - PIB",
      "url": "https://news.google.com/rss/articles/CBMiekFVX3lxTE8wUkFpOEY2eFJ1VmxjM1JtT2pyaWEzS2M2ODd3b184cWlfMEJIRFF4dU9WMEpXdDFhc2JzejVTS0Y0MDlKN0dCS0NIX1FKbXpjeEVBaERPYjBidjNJTm9QekJ5WkpEcTF0SEtUSDVGOHdITEQ1dk1hNlNn?oc=5",
      "description": "<a href=\"https://news.google.com/rss/articles/CBMiekFVX3lxTE8wUkFpOEY2eFJ1VmxjM1JtT2pyaWEzS2M2ODd3b184cWlfMEJIRFF4dU9WMEpXdDFhc2JzejVTS0Y0MDlKN0dCS0NIX1FKbXpjeEVBaERPYjBidjNJTm9QekJ5WkpEcTF0SEtUSDVGOHdITEQ1dk1hNlNn?oc=5\"...",
      "source": "PIB",
      "image": "",
      "lang": "en",
      "pubDate": "2026-04-22T06:26:56.913Z"
    },
    {
      "title": "Securing Farming Futures: How Crop Insurance Is Strengthening Livelihoods for Women Farmers - UNDP",
      "url": "https://news.google.com/rss/articles/CBMiugFBVV95cUxQMnhneTlmRG9LZFdKRGdvMDY4TFI4d3FVZXlzXzRjVXJRNmlTVUg0T1k5bFZQUmJ3Z1JvZ1BUS1pyTDA1T1V6UTRvQWEyNHc5RllBdUJrdFAwQWl6YkVsNlpSbUNvV2ZWS3FnNjB1NlhzOFpaZDNDaVVieC1vTXpWcjNJQzhmWkZQY21ZdzM1QV9BN2xzLW43R3JpcGxVeFFkLVI3cno1T3F5Ukd1Vy1pMmZEV0FVUmJlMXc?oc=5",
      "description": "<a href=\"https://news.google.com/rss/articles/CBMiugFBVV95cUxQMnhneTlmRG9LZFdKRGdvMDY4TFI4d3FVZXlzXzRjVXJRNmlTVUg0T1k5bFZQUmJ3Z1JvZ1BUS1pyTDA1T1V6UTRvQWEyNHc5RllBdUJrdFAwQWl6YkVsNlpSbUNvV2ZWS3FnNjB1NlhzOFpaZDNDaVVieC1vTX...",
      "source": "UNDP",
      "image": "",
      "lang": "en",
      "pubDate": "2026-04-22T06:26:56.913Z"
    },
    {
      "title": "When a war far away raises cost of farming in India - Down To Earth",
      "url": "https://news.google.com/rss/articles/CBMimgFBVV95cUxOdEt3bER5UFhuZTgxeUxMUmpSN2Z4Q2sweDRXSVFBVHF0Z25Jcld5UU53dmlScVhlT29WczBmV2xZRXlzVDNyVGRqTE54dDZ5NDRnQmFsSjZPbGUzUlJHQlNlUXdlb1QzVW1sR19vUExjc0Z3bHlKT0tsSlB3SVF3Z014YVJLcFpIUVN3eWlmNU1uZ0N5LS1jTThB0gGnAUFVX3lxTFBDVHFXUGhsZzJ3R0pweWs2M0VrRzNvWjlfd2pIUXRYRmNja0w2czBXMXBuVzhmc3Q0LU9PNTh4cDNQdmd3ZHpUN0lFQzNwS3pvUHdxUW5yRnNmajFkUXR3Z0w1Ym13QUtmbzNObmhYN1JCU0FXamlONGZ5UGY1bWV1Z1l1TDBvQ09SRmVXaGZ2VzVfYTNmY2xNR293WVJET3VJTTZiRGNR?oc=5",
      "description": "<a href=\"https://news.google.com/rss/articles/CBMimgFBVV95cUxOdEt3bER5UFhuZTgxeUxMUmpSN2Z4Q2sweDRXSVFBVHF0Z25Jcld5UU53dmlScVhlT29WczBmV2xZRXlzVDNyVGRqTE54dDZ5NDRnQmFsSjZPbGUzUlJHQlNlUXdlb1QzVW1sR19vUExjc0Z3bHlKT0tsSlB3SV...",
      "source": "Down To Earth",
      "image": "",
      "lang": "en",
      "pubDate": "2026-04-22T06:26:56.913Z"
    },
    {
      "title": "M.S. Swaminathan | Green Revolution, India, Contribution, Agriculture, Genetics, & Awards - Britannica",
      "url": "https://news.google.com/rss/articles/CBMiYkFVX3lxTE1zazg4czd6cUhxVnFHblJTZzBTQmFGeU9MNlVzM3VqdUxZQUJpRW40NWc1X0dsUGp4bmQtdWdDMTduR3pTRjZWbHhTeFU2SGZpbVotbHBOSkJtb0RZRnBFaVZ3?oc=5",
      "description": "<a href=\"https://news.google.com/rss/articles/CBMiYkFVX3lxTE1zazg4czd6cUhxVnFHblJTZzBTQmFGeU9MNlVzM3VqdUxZQUJpRW40NWc1X0dsUGp4bmQtdWdDMTduR3pTRjZWbHhTeFU2SGZpbVotbHBOSkJtb0RZRnBFaVZ3?oc=5\" target=\"_blank\">M.S. Swaminatha...",
      "source": "Britannica",
      "image": "",
      "lang": "en",
      "pubDate": "2026-04-22T06:26:56.913Z"
    },
    {
      "title": "Budget 2026 for agriculture: The opportunity to strengthen India’s crop protection backbone - The Times of India",
      "url": "https://news.google.com/rss/articles/CBMihgJBVV95cUxQRHZiSnVQU0pKQ29tbjNEUGp6QzFkYWp3ZDlySFo2S1RWUHU0RjRHakxiTHBtQTNSeUoyUXFVUFBjTWFOdmtwNFd6ZWpaUXdyYVNaRzEwc2NYV2NUYTdLVDViNjI2RmR3RG5kdnlZZmoxNGNYelU5YzhZb2R0TGtLZ1I3dkRoMHItODlEdW96dU1ZVjlteVdCTXBKX1dHUlBYUFlqT25OSTBXNmVZVVd1dHdSTE1yNF9ZNGNHRmFnTzBhSy1GVjdWUVVwaWEwRWRMa1hDVDMtQ2x4dHZQbkYzUG5RSHZEUWlVU1M3OGhWalBodEIxcHpXRVdoWENYMWlNWmhEblpn0gGLAkFVX3lxTE8tazh4dHJFc3lRbEc3WGJmTC0yM0ZiYXgwektia2R1U3hjWnAyN1ozTlAxQ2JoNW1lX012VkFNM3I2UlBhYUNEUjRhcnhGVnFjZnl3LXZmRmF2cmFyemFmRlBIWHI2a2ttTG9JQ0JJQ2ZtSnYwYVc4Y2Q0YWFmaG1USEhXazhuWUI2d0t4RGhmN0FTY3I4cGZlX0psNXpEaFlRMmFNWHlJMTRUZlQyY2J4eXY2U0NuSjNpd01pcUNVMkdkbWpqVFd1NFhtX1FUa2x2WEN3NnFabjdHVlVidVJISjNUWDFiWnJZeFQzQ1J2STFaWWJrMFRfYnV1RDZEeS12SlZSUU1VY0VWVQ?oc=5",
      "description": "<a href=\"https://news.google.com/rss/articles/CBMihgJBVV95cUxQRHZiSnVQU0pKQ29tbjNEUGp6QzFkYWp3ZDlySFo2S1RWUHU0RjRHakxiTHBtQTNSeUoyUXFVUFBjTWFOdmtwNFd6ZWpaUXdyYVNaRzEwc2NYV2NUYTdLVDViNjI2RmR3RG5kdnlZZmoxNGNYelU5YzhZb2R0TG...",
      "source": "The Times of India",
      "image": "",
      "lang": "en",
      "pubDate": "2026-04-22T06:26:56.913Z"
    },
    {
      "title": "Congress questions impact of India-U.S. trade pact on agriculture, crop prices - The Hindu",
      "url": "https://news.google.com/rss/articles/CBMizwFBVV95cUxQME9VbENPWWdlRU55d1Q1WHNJenlUWEJRbC1ldm5xSW5oSmoxb3BMelBtaEJGY2pQbHJ4dHVXdzcyODZIa3ZmQmhUVnBKV1Q3YTI0ODhmR19qb3VxSWloMUloLTBoQ1pLN3ZnNDNtaS02eEFsODZEdU81RERuZkdGRnE5elpfQW40bmxUcGJkTUwxUjZaWkR0Uk1ZaXloV2R2cnNxOGRLZ21Ec0F3OTR3TkxaMGhSTWNveTI2Vmd0dEhaNmw3dXNqSkt5SFREYVHSAdYBQVVfeXFMUHNFcVA2UC1MMkY3UnROWUZWVGotanRRUHpZOV9ua20tMFRmQTEyNGxoa3dmeHVlNE1DekRJSEUzNlh0SEFSOTVWNm52VWxfYUt0QWJNYjZoRllBQnV5dDRrNW9ObTNoVnRRQnYyVjEzRDdYbldfYjdTLUJOX2V6SjJLcmZGbGhPZnFiU2Nib3dUb2xSeEhuRG12SC14eWw2dndESUFGZnlDVVprMUZHWENoWkF1QTNBN2lMaE5tb3hnektiQTAwNUtWQVpmQ0FvQWJkMnVIQQ?oc=5",
      "description": "<a href=\"https://news.google.com/rss/articles/CBMizwFBVV95cUxQME9VbENPWWdlRU55d1Q1WHNJenlUWEJRbC1ldm5xSW5oSmoxb3BMelBtaEJGY2pQbHJ4dHVXdzcyODZIa3ZmQmhUVnBKV1Q3YTI0ODhmR19qb3VxSWloMUloLTBoQ1pLN3ZnNDNtaS02eEFsODZEdU81RERuZk...",
      "source": "The Hindu",
      "image": "",
      "lang": "en",
      "pubDate": "2026-04-22T06:26:56.913Z"
    },
    {
      "title": "Indian farmers dress up as bears to protect crops from monkeys - Al Jazeera",
      "url": "https://news.google.com/rss/articles/CBMiswFBVV95cUxNRjhDSDdVcTRrMVJzUG0wZTEzSFRWMWs4dzNjRTBaczRmVktjSmFma0ZMbGdMOTA4UUFwbk5OMXJ2aFliMTkwa2tkcE5Wd2E1Y29pVEtVNXNjbFo5UkhwWl8xdGx5STRIa2tWTXpHYzZ0TVdqeGk1blZ2WTI1UENuRjVsVVJyV0xkZTZlWkN2SjB0SGlYeFhXaFpnWF9CZjUwRnVNNk9jcWxnanE3RlJDQjlXSdIBuAFBVV95cUxQeXFHZ0c0Yl85eU8wRjdvMXlYOHN3RW5XWVUxNXl4M2xac2loNC1UbllyZmdBMGxXWU8xR1VDU0F1cFlwSl9sbTVZek9IU04yMTJ1bkVobWRRaGFCSlM5c0o3NHh3T0Voa3dyWGFMck5YektZdXBCZ2k4MXFMblpKU1VwUVZoa2pTeHQ5T1NQQTRKTkpYS2tid1Z1Vm5qRldyUnFGX0VkQV9iQU1NQkhKOWY4bDU5MUdO?oc=5",
      "description": "<a href=\"https://news.google.com/rss/articles/CBMiswFBVV95cUxNRjhDSDdVcTRrMVJzUG0wZTEzSFRWMWs4dzNjRTBaczRmVktjSmFma0ZMbGdMOTA4UUFwbk5OMXJ2aFliMTkwa2tkcE5Wd2E1Y29pVEtVNXNjbFo5UkhwWl8xdGx5STRIa2tWTXpHYzZ0TVdqeGk1blZ2WTI1UE...",
      "source": "Al Jazeera",
      "image": "",
      "lang": "en",
      "pubDate": "2026-04-22T06:26:56.913Z"
    }
  ],
  "articles": [
    {
      "title": "मध्यप्रदेश पुलिस का बड़ा अभियान, कई जिलों में छापेमारी कर 178 गौवंश मुक्त; आरोपियों पर कार्रवाई",
      "url": "https://www.krishakjagat.org/news/major-operation-by-madhya-pradesh-police-178-cattle-rescued-in-raids-across-several-districts-action-taken-against-accused/",
      "description": "KRISHAK JAGAT | National Agriculture Hindi Newspaper 22 अप्रैल 2026, भोपाल: मध्यप्रदेश पुलिस का बड़ा अभियान, कई जिलों में छापेमारी कर 178 गौवंश मुक्त; आरोपियों पर कार्रवाई &#8211; मध्यप्रदेश पुलिस ने प्रदेशभर में अवैध गौ...",
      "source": "Krishak Jagat",
      "image": "https://www.krishakjagat.org/wp-content/uploads/2026/04/Untitled-1-321.jpg",
      "lang": "hi",
      "pubDate": "2026-04-22T06:26:46.994Z"
    },
    {
      "title": "मध्यप्रदेश में गेहूं खरीदी तेज: अब तक 1.88 लाख किसानों से 81.76 लाख क्विंटल उपार्जन, 1083 करोड़ भुगतान",
      "url": "https://www.krishakjagat.org/news/wheat-procurement-accelerates-in-madhya-pradesh-81-76-lakh-quintals-procured-from-1-88-lakh-farmers-so-far-%e2%82%b91083-crore-paid/",
      "description": "KRISHAK JAGAT | National Agriculture Hindi Newspaper 22 अप्रैल 2026, भोपाल: मध्यप्रदेश में गेहूं खरीदी तेज: अब तक 1.88 लाख किसानों से 81.76 लाख क्विंटल उपार्जन, 1083 करोड़ भुगतान &#8211; मध्यप्रदेश के खाद्य, नागरिक आपूर्...",
      "source": "Krishak Jagat",
      "image": "https://www.krishakjagat.org/wp-content/uploads/2026/04/liioi.jpg",
      "lang": "hi",
      "pubDate": "2026-04-22T06:26:46.994Z"
    },
    {
      "title": "आज का धान मंडी रेट (21 अप्रैल 2026)",
      "url": "https://www.krishakjagat.org/mandi-rate/todays-paddy-market-rates-april-21-2026/",
      "description": "KRISHAK JAGAT | National Agriculture Hindi Newspaper 21 अप्रैल 2026, नई दिल्ली: आज का धान मंडी रेट (21 अप्रैल 2026) – नीचे दी गई तालिका में पूरे भारत में धान की मंडी दरें हैं। इसमें धान की न्यूनतम, अधिकतम और मोडल दर का उ...",
      "source": "Krishak Jagat",
      "image": "https://www.krishakjagat.org/wp-content/uploads/2026/04/Untitled-1-316.jpg",
      "lang": "hi",
      "pubDate": "2026-04-22T06:26:46.994Z"
    },
    {
      "title": "मध्यप्रदेश: रतलाम में नरवाई प्रबंधन अभियान तेज, 300 किसानों को डीकंपोजर वितरण, खेतों में दिया गया लाइव डेमो",
      "url": "https://www.krishakjagat.org/news/madhya-pradesh-stubble-management-campaign-intensifies-in-ratlam-decomposers-distributed-to-300-farmers-live-demonstrations-conducted-in-fields/",
      "description": "KRISHAK JAGAT | National Agriculture Hindi Newspaper 21 अप्रैल 2026, रतलाम: मध्यप्रदेश: रतलाम में नरवाई प्रबंधन अभियान तेज, 300 किसानों को डीकंपोजर वितरण, खेतों में दिया गया लाइव डेमो &#8211; मध्यप्रदेश के रतलाम जिले में...",
      "source": "Krishak Jagat",
      "image": "https://www.krishakjagat.org/wp-content/uploads/2026/04/Untitled-1-320.jpg",
      "lang": "hi",
      "pubDate": "2026-04-22T06:26:46.994Z"
    },
    {
      "title": "Success Story: PRO की नौकरी छोड़ किसान बने राहुल, अब 10 एकड़ में अश्वगंधा उगाकर कमा रहे लाखों",
      "url": "https://www.krishakjagat.org/news/success-story-rahul-quits-pro-job-to-become-a-farmer-now-earns-lakhs-by-cultivating-ashwagandha-on-10-acres/",
      "description": "KRISHAK JAGAT | National Agriculture Hindi Newspaper 21 अप्रैल 2026, भोपाल: Success Story: PRO की नौकरी छोड़ किसान बने राहुल, अब 10 एकड़ में अश्वगंधा उगाकर कमा रहे लाखों &#8211; मध्य प्रदेश के सागर जिले के देवरी विकासखंड...",
      "source": "Krishak Jagat",
      "image": "https://www.krishakjagat.org/wp-content/uploads/2026/04/Untitled-1-319.jpg",
      "lang": "hi",
      "pubDate": "2026-04-22T06:26:46.994Z"
    },
    {
      "title": "IMD Bhopal Alert: मध्य प्रदेश में तेज गर्मी का कहर, खजुराहो में 43°C पहुंचा पारा; IMD ने जारी किया अलर्ट",
      "url": "https://www.krishakjagat.org/news/imd-bhopal-alert-intense-heatwave-grips-madhya-pradesh-mercury-hits-43c-in-khajuraho-imd-issues-alert/",
      "description": "KRISHAK JAGAT | National Agriculture Hindi Newspaper 21 अप्रैल 2026, भोपाल: IMD Bhopal Alert: मध्य प्रदेश में तेज गर्मी का कहर, खजुराहो में 43°C पहुंचा पारा; IMD ने जारी किया अलर्ट &#8211; मध्य प्रदेश में मौसम का मिजाज त...",
      "source": "Krishak Jagat",
      "image": "https://www.krishakjagat.org/wp-content/uploads/2026/04/Untitled-1-317.jpg",
      "lang": "hi",
      "pubDate": "2026-04-22T06:26:46.994Z"
    },
    {
      "title": "Weather Update: देश में मौसम का डबल अटैक, 44°C की लू के बीच कई राज्यों में तूफानी बारिश का अलर्ट; IMD ने दी चेतावनी",
      "url": "https://www.krishakjagat.org/national-news/weather-update-double-whammy-for-the-nation-stormy-rain-alert-issued-for-several-states-amidst-44c-heatwave-imd-issues-warning/",
      "description": "KRISHAK JAGAT | National Agriculture Hindi Newspaper 21 अप्रैल 2026, नई दिल्ली: Weather Update: देश में मौसम का डबल अटैक, 44°C की लू के बीच कई राज्यों में तूफानी बारिश का अलर्ट; IMD ने दी चेतावनी &#8211; भारतीय मौसम विज्...",
      "source": "Krishak Jagat",
      "image": "https://www.krishakjagat.org/wp-content/uploads/2026/04/Untitled-1-313.jpg",
      "lang": "hi",
      "pubDate": "2026-04-22T06:26:46.994Z"
    },
    {
      "title": "Wheat Export: सरकार का बड़ा फैसला, 25 लाख टन अतिरिक्त गेहूं निर्यात को मंजूरी, किसानों को मिलेगा फायदा",
      "url": "https://www.krishakjagat.org/national-news/wheat-exports-major-government-decision-approval-granted-for-export-of-2-5-million-tonnes-of-additional-wheat-farmers-to-benefit/",
      "description": "KRISHAK JAGAT | National Agriculture Hindi Newspaper 21 अप्रैल 2026, नई दिल्ली: Wheat Export: सरकार का बड़ा फैसला, 25 लाख टन अतिरिक्त गेहूं निर्यात को मंजूरी, किसानों को मिलेगा फायदा &#8211; भारत सरकार ने अतिरिक्त 25 लाख...",
      "source": "Krishak Jagat",
      "image": "https://www.krishakjagat.org/wp-content/uploads/2026/04/Untitled-1-312.jpg",
      "lang": "hi",
      "pubDate": "2026-04-22T06:26:46.994Z"
    },
    {
      "title": "ग्रीष्मकालीन फसलों का बढ़ा रकबा, 69.06 लाख हेक्टेयर तक पहुंची बुवाई; दलहन और मोटे अनाज में भी तेजी",
      "url": "https://www.krishakjagat.org/national-news/area-under-summer-crops-expands-sowing-reaches-69-06-lakh-hectares-with-a-surge-in-pulses-and-coarse-cereals-as-well/",
      "description": "KRISHAK JAGAT | National Agriculture Hindi Newspaper 21 अप्रैल 2026, नई दिल्ली: ग्रीष्मकालीन फसलों का बढ़ा रकबा, 69.06 लाख हेक्टेयर तक पहुंची बुवाई; दलहन और मोटे अनाज में भी तेजी &#8211; कृषि एवं किसान कल्याण मंत्रालय के...",
      "source": "Krishak Jagat",
      "image": "https://www.krishakjagat.org/wp-content/uploads/2026/04/Untitled-1-311.jpg",
      "lang": "hi",
      "pubDate": "2026-04-22T06:26:46.994Z"
    },
    {
      "title": "टिंडा की फसल पर मंडराया डाउनी मिल्ड्यू का खतरा, किसान ऐसे करें तुरंत बचाव",
      "url": "https://www.krishakjagat.org/crop-cultivation/threat-of-downy-mildew-looms-over-tinda-crop-farmers-should-take-immediate-preventive-measures/",
      "description": "KRISHAK JAGAT | National Agriculture Hindi Newspaper 21 अप्रैल 2026, नई दिल्ली: टिंडा की फसल पर मंडराया डाउनी मिल्ड्यू का खतरा, किसान ऐसे करें तुरंत बचाव &#8211; टिंडा (राउण्ड गार्ड) की फसल में इन दिनों पत्तियों के पीले ...",
      "source": "Krishak Jagat",
      "image": "https://www.krishakjagat.org/wp-content/uploads/2026/04/Untitled-1-310.jpg",
      "lang": "hi",
      "pubDate": "2026-04-22T06:26:46.994Z"
    },
    {
      "title": "साप्ताहिक मंडी भाव और क्रॉप प्राइस विश्लेषण: अनाज, दालों और तेलहन फसलों के भाव में उतार-चढ़ाव - Tractor Junction",
      "url": "https://news.google.com/rss/articles/CBMimwFBVV95cUxOSnliRVM3ZmlnTXpmS3FldERza0JSM3FFOW1pSHlEdDdYVjVudEN4Sm1LY3NWNEhzbVJ2blJ0VmU5dnBITURQYkw5TnJBa2hQb0o5RmRPRmJCTEx3QVVLcVB2bGlBV0d2N3hUc3kyVDF3SG1GelZzWC05cnk4Rkt4eWdQbHVsckdIWFNnVlFZZWlMajB5dTFucmhKc9IBowFBVV95cUxQRnBFUTF6Mm8xTjF1RGhYcXN5QVJVTlMxdFdtMlFEZEQzQm11RFlGcEtLSHdIVk5CUlpPMF9CZkRuSTN5NGh4OG80dTZVRmlvNzBNbUtlZzJiWVVuWHYwREtlTjd5RUhFMGM1Nkx0Y3QxeHB4LVZYZGtwVFdWOE9KUTVTWjJfMUpJZkhKYmlCVWYwOXoyR25MYjVFMVI3elFvZTZF?oc=5",
      "description": "<a href=\"https://news.google.com/rss/articles/CBMimwFBVV95cUxOSnliRVM3ZmlnTXpmS3FldERza0JSM3FFOW1pSHlEdDdYVjVudEN4Sm1LY3NWNEhzbVJ2blJ0VmU5dnBITURQYkw5TnJBa2hQb0o5RmRPRmJCTEx3QVVLcVB2bGlBV0d2N3hUc3kyVDF3SG1GelZzWC05cnk4Rk...",
      "source": "Tractor Junction",
      "image": "",
      "lang": "hi",
      "pubDate": "2026-04-22T06:26:51.886Z"
    },
    {
      "title": "सरसों किसानों की हुई बल्ले-बल्ले, MSP से ज्यादा हुआ मंडी भाव...ईरान-अमेर‍िका युद्ध से बाजार में तेजी - Kisan Tak",
      "url": "https://news.google.com/rss/articles/CBMizAFBVV95cUxQb0dXUGh3NWlidEVKNVNOQ3poVkFJRVZFT2hRZFNVUXVERFltaHBEeEZtcVlhblhYNjBoaG9UejczLWJDcXJrSWFIV0Rna3hwN3lyZE01VklRUnV6bDFjTEZYN1E5LUtXNHNVRms4YlFpTXdFUGFhUmxoTWJIelpyWXcwWnZSQ1FjWmxlRFF1OFhUMGlvSlY0Nndmc0g1S1ozTnl4OHhYbHZTdW9zT0dERlJHVWxybVBRN1RtNzBacUpTYzZaR1MxdUhTcjPSAdIBQVVfeXFMTS1wV1lGa3hsd1VEbGZGSVhDZFBpUG45UWRFYXdDR0U1QXF5RDZ6RUJZQkpXUzNIcUpGRzZwQ2sybjhzOGVadHNvYUstaGxXNzEySWlrVm84Y3FrdkFMQjMyRkYtMUpES3otcnd3amdVMnVyWWd6U1NJZnJXV0dNMkpNSS1uQ3ZzZTQtVmtEWjlXUF9KdlBGNzl4dHNRbVczaWc3UTBWRVV6dmdYWTZwOW1Qb09LRlFLamdmX1VsU1UyeEg3V2FfcmVCeV9kaWM1OExR?oc=5",
      "description": "<a href=\"https://news.google.com/rss/articles/CBMizAFBVV95cUxQb0dXUGh3NWlidEVKNVNOQ3poVkFJRVZFT2hRZFNVUXVERFltaHBEeEZtcVlhblhYNjBoaG9UejczLWJDcXJrSWFIV0Rna3hwN3lyZE01VklRUnV6bDFjTEZYN1E5LUtXNHNVRms4YlFpTXdFUGFhUmxoTWJIel...",
      "source": "Kisan Tak",
      "image": "",
      "lang": "hi",
      "pubDate": "2026-04-22T06:26:51.887Z"
    },
    {
      "title": "5 काम जो किसानों के लिए भारत-विस्तार प्लेटफॉर्म से आसान हो जाएंगे? ये काम कैसे करेगा - News18 Hindi",
      "url": "https://news.google.com/rss/articles/CBMi1AFBVV95cUxPUmhaNnRSQkIzQWtLWDVWaWZzd1FmUURXZFdWNjFyMmVicGpaajYzTXpWaUdXd2dvMHNJNVU5bmhvOG1md3N5SEw5WEVzdEhCR0JnM0stSTFCLTZSVVVCYi05SVo2Ykd0NElQU1AyR2U3NU1uREtpMERlbmgxbVRLOWwyUUR5S2Q5VGFEeldMSjF4WDVoQ2NrTFYtUmxoMmkyWGU1cmpGcGYwUmw0Szl6bXlENkxEUHNSQW1nenptLWFfdWJOckgyWVlqaFAzR3Zmczlqd9IB2gFBVV95cUxObk1Kem5nY1pVbDI3blZWRjR1a2xFQU83NTJoYXJNQ0J5TXZBNEI0QnlfR1V0dVduODN6d2N4XzR5eWdfeW1DR3o3Z21IZUUwd3JPb0NJdm9kcFg1eVFlUFhacmFkZFg1UWh4Z2Q1UWpCUU5Ba21VT2g2TGgzci1uc2xsSFhqMjVwbThKbjRnSGpNRU9rRU05VVE5NU1WcW1tUldsV2JQWWZJWUlSOER6S2lRMU9xOG5QZjJLQ210Uy1wZWwzQXNTQ3dyOGJZWWdKbWx1bUtGLTNIUQ?oc=5",
      "description": "<a href=\"https://news.google.com/rss/articles/CBMi1AFBVV95cUxPUmhaNnRSQkIzQWtLWDVWaWZzd1FmUURXZFdWNjFyMmVicGpaajYzTXpWaUdXd2dvMHNJNVU5bmhvOG1md3N5SEw5WEVzdEhCR0JnM0stSTFCLTZSVVVCYi05SVo2Ykd0NElQU1AyR2U3NU1uREtpMERlbmgxbV...",
      "source": "News18 Hindi",
      "image": "",
      "lang": "hi",
      "pubDate": "2026-04-22T06:26:51.887Z"
    },
    {
      "title": "Mandi News: किसानों की बल्ले-बल्ले, सरसों का भाव 6850 रुपए तक पहुंचा, जानें मंडी रेट - Patrika News",
      "url": "https://news.google.com/rss/articles/CBMisgFBVV95cUxQVjVxR1JGZFN0RnE5azJ5Z1VLTE0xZG1FYjA0Vnc5ZkhvWVpKVVhKRzQ2VVl3NVJPblBCQlM4RXhXWU5ZM1FBTlA3Ty1pZjI2aTJ0YmhRMGV6UzJMNW9vZUlGY0RpQjByRTdhSTg4dW5ZQ0xpX3I1S0xscDVIMlRHZEVsNllvYWxleFZCU0tQNGpxSFJDM2N5dEs0YndrYTJ6SDNPUUdBcTFrYkFxQ1RxM3FB0gG3AUFVX3lxTE1fM2VwMm8xV1MweEtNOTh5VHF5XzB5NG9HVHB6dDVrMEJhWWhNVU5CXzN6ZWowMjc4NVVwQndqTjdLamc3YlRUV1cyT1Zlc3FnTTgxX19kcWthTnUxX2VhR1FDNkJlRldYVlQ3MFJqbU56LW1jLVFQMVU4R2YySEF3cDBFWkxEdnlsbzlkSHF1T05GVTgyRUtOdDFoUV9qS19Yak54cDE1R0F6R1RRcDE0YjVqdXNXRQ?oc=5",
      "description": "<a href=\"https://news.google.com/rss/articles/CBMisgFBVV95cUxQVjVxR1JGZFN0RnE5azJ5Z1VLTE0xZG1FYjA0Vnc5ZkhvWVpKVVhKRzQ2VVl3NVJPblBCQlM4RXhXWU5ZM1FBTlA3Ty1pZjI2aTJ0YmhRMGV6UzJMNW9vZUlGY0RpQjByRTdhSTg4dW5ZQ0xpX3I1S0xscDVIMl...",
      "source": "Patrika News",
      "image": "",
      "lang": "hi",
      "pubDate": "2026-04-22T06:26:51.887Z"
    },
    {
      "title": "155261 पर किसान कल से करें कॉल, AI बताएगा मौसम, सरकारी योजनाओं, मंडी भाव, फसल का हाल - NDTV.in",
      "url": "https://news.google.com/rss/articles/CBMixAFBVV95cUxPWnUxRkp2SkpibzdraWdQQWltZEloSjdDbEF6VHZmU1BEcU1BbERJSUI1ZVo1MUlkejVYX3lNY1o5QVpsNTRUSTN1YllaaHdnUS1TQk16aEpMRG0zME1NSkUzY0c4NjNJWlJsOEtCdGpib3phOFlsMENrQzJSMVRuNV92WTllYS1TOEwtRkgweDZfMzFDZFVqQ0wxTzU4N3BYN0MyRFR4ZW1waWJDdVJkYUY1T3ItQllRa1l3M0JWNXhfT3Jm0gHMAUFVX3lxTE9ySG5ubUJGZnJjZE9KTzNMSFdHa3RZT0VxQ01sM0wwOGdKbjlLd3BaN0Q1SHR4NEFwWEh0dm5VMHJfRWE1bXQ4UE00UHNOU2t2NE1TaHp4UERUMzd6RnVPOTB5aXh5c0s1SkZQZHFrbkE2eFhsbEc5dG5USUVIOFMxTW9JV2pZQmgxNFBzeGNHLTl3OTgyTlJCQlltS2tXejRzbUpBUFhCVTNDc25hN3dxanNULUdtc25lUmU4NlBsMFVWVU9NMkRYbXJ1Zg?oc=5",
      "description": "<a href=\"https://news.google.com/rss/articles/CBMixAFBVV95cUxPWnUxRkp2SkpibzdraWdQQWltZEloSjdDbEF6VHZmU1BEcU1BbERJSUI1ZVo1MUlkejVYX3lNY1o5QVpsNTRUSTN1YllaaHdnUS1TQk16aEpMRG0zME1NSkUzY0c4NjNJWlJsOEtCdGpib3phOFlsMENrQzJSMV...",
      "source": "NDTV.in",
      "image": "",
      "lang": "hi",
      "pubDate": "2026-04-22T06:26:51.887Z"
    }
  ]
}